Workbook

Sheet Products
A1: Product ID | B1: Book Name | C1: Authors | D1: Book Type | E1: Published Year | F1: Purchase Price | G1: Margin | H1: Selling Price | I1: 0.3 | J1: 0.5 | K1: 0.7
A2: 1 | B2: The Discovery of India | C2: Jawaharlal Nehru | D2: Hard Cover | E2: 1946 | F2: 599.95 | G2: 0.3 | H2: =F2+(G2*F2) -> 779.935 | I2: =$F2+($F2*I$1) -> 779.935 | J2: =$F2+($F2*J$1) -> 899.925 | K2: =$F2+($F2*K$1) -> 1019.915
A3: 2 | B3: The Story of my Experiments with Truth | C3: Mahatma Gandhi | D3: Hard Cover | E3: 1927 | F3: 159 | G3: 0.3 | H3: =F3+(G3*F3) -> 206.7 | I3: =$F3+($F3*I$1) -> 206.7 | J3: =$F3+($F3*J$1) -> 238.5 | K3: =$F3+($F3*K$1) -> 270.3
A4: 3 | B4: Glimpses of World History | C4: Jawaharlal Nehru | D4: Hard Cover | E4: 1934 | F4: 750.459 | G4: 0.2 | H4: =F4+(G4*F4) -> 900.5508 | I4: =$F4+($F4*I$1) -> 975.5967 | J4: =$F4+($F4*J$1) -> 1125.6885 | K4: =$F4+($F4*K$1) -> 1275.7803
A5: 4 | B5: A Guide to Health | C5: Mahatma Gandhi | D5: Hard Cover | E5: 1921 | F5: 250 | G5: 0.15 | H5: =F5+(G5*F5) -> 287.5 | I5: =$F5+($F5*I$1) -> 325 | J5: =$F5+($F5*J$1) -> 375 | K5: =$F5+($F5*K$1) -> 425
A6: 5 | B6: Wings of Fire | C6: APJ Abdul Kalam, Arun Tiwari | D6: Hard Cover | E6: 1999 | F6: 1275.2488 | G6: 0.1 | H6: =F6+(G6*F6) -> 1402.7737 | I6: =$F6+($F6*I$1) -> 1657.8234 | J6: =$F6+($F6*J$1) -> 1912.8732 | K6: =$F6+($F6*K$1) -> 2167.923
A7: 6 | B7: The Discovery of India | C7: Jawaharlal Nehru | D7: Soft Cover | E7: 1946 | F7: 499 | G7: 0.3 | H7: =F7+(G7*F7) -> 648.7 | I7: =$F7+($F7*I$1) -> 648.7 | J7: =$F7+($F7*J$1) -> 748.5 | K7: =$F7+($F7*K$1) -> 848.3
A8: 7 | B8: The Story of my Experiments with Truth | C8: Mahatma Gandhi | D8: Soft Cover | E8: 1927 | F8: 109 | G8: 0.3 | H8: =F8+(G8*F8) -> 141.7 | I8: =$F8+($F8*I$1) -> 141.7 | J8: =$F8+($F8*J$1) -> 163.5 | K8: =$F8+($F8*K$1) -> 185.3
A9: 8 | B9: Glimpses of World History | C9: Jawaharlal Nehru | D9: Soft Cover | E9: 1934 | F9: 650 | G9: 0.2 | H9: =F9+(G9*F9) -> 780 | I9: =$F9+($F9*I$1) -> 845 | J9: =$F9+($F9*J$1) -> 975 | K9: =$F9+($F9*K$1) -> 1105
A10: 9 | B10: A Guide to Health | C10: Mahatma Gandhi | D10: Soft Cover | E10: 1921 | F10: 220 | G10: 0.15 | H10: =F10+(G10*F10) -> 253 | I10: =$F10+($F10*I$1) -> 286 | J10: =$F10+($F10*J$1) -> 330 | K10: =$F10+($F10*K$1) -> 374
A11: 10 | B11: Wings of Fire | C11: APJ Abdul Kalam, Arun Tiwari | D11: Soft Cover | E11: 1999 | F11: 1200 | G11: 0.1 | H11: =F11+(G11*F11) -> 1320 | I11: =$F11+($F11*I$1) -> 1560 | J11: =$F11+($F11*J$1) -> 1800 | K11: =$F11+($F11*K$1) -> 2040
A12: 11 | B12: The Discovery of India | C12: Jawaharlal Nehru | D12: e-book | E12: 2004 | F12: 250 | G12: 0.3 | H12: =F12+(G12*F12) -> 325 | I12: =$F12+($F12*I$1) -> 325 | J12: =$F12+($F12*J$1) -> 375 | K12: =$F12+($F12*K$1) -> 425
A13: 12 | B13: The Story of my Experiments with Truth | C13: Mahatma Gandhi | D13: e-book | E13: 2004 | F13: 50 | G13: 0.3 | H13: =F13+(G13*F13) -> 65 | I13: =$F13+($F13*I$1) -> 65 | J13: =$F13+($F13*J$1) -> 75 | K13: =$F13+($F13*K$1) -> 85
... A16: 15 | B16: Wings of Fire | C16: APJ Abdul Kalam, Arun Tiwari | D16: e-book | E16: 2005 | F16: 500 | G16: 0.1 | H16: =F16+(G16*F16) -> 550 | I16: =$F16+($F16*I$1) -> 650 | J16: =$F16+($F16*J$1) -> 750 | K16: =$F16+($F16*K$1) -> 850
A18: =COUNT(A2:A16) -> 15 | B18: =COUNTA(B2:B16) -> 15 | C18: =COUNTBLANK(F18:G19) -> 4

Sheet Employees
B1: =MONTH(B2) -> 1 | C1: =MONTH(C2) -> 1 | D1: =MONTH(D2) -> 1 | E1: =MONTH(E2) -> 1 | F1: =MONTH(F2) -> 1 | G1: =MONTH(G2) -> 1 | H1: =MONTH(H2) -> 1 | I1: =MONTH(I2) -> 1 | ... NB1: =MONTH(NB2) -> 12 | NF1: 1 | NG1: 2 | NH1: 3 | NI1: 4 | NJ1: 5 | NK1: 6 | NL1: 7 | NM1: 8 | NN1: 9 | NO1: 10 | NP1: 11 | NQ1: 12 | NU1: 1 | NV1: 2 | NW1: 3 | NX1: 4 | NY1: 5 | NZ1: 6 | OA1: 7 | OB1: 8 | OC1: 9 | OD1: 10 | OE1: 11 | OF1: 12
A2: Employee Name | B2: 41275 | C2: 41276 | D2: 41277 | E2: 41278 | F2: 41279 | G2: 41280 | H2: 41281 | I2: 41282 | J2: 41283 | K2: 41284 | L2: 41285 | M2: 41286 | N2: 41287 | O2: 41288 | P2: 41289 | Q2: 41290 | R2: 41291 | S2: 41292 | T2: 41293 | U2: 41294 | V2: 41295 | W2: 41296 | X2: 41297 | Y2: 41298 | Z2: 41299 | AA2: 41300 | AB2: 41301 | AC2: 41302 | AD2: 41303 | AE2: 41304 | AF2: 41305 | AG2: 41306 | AH2: 41307 | AI2: 41308 | AJ2: 41309 | AK2: 41310 | AL2: 41311 | AM2: 41312 | AN2: 41313 | AO2: 41314 | AP2: 41315 | AQ2: 41316 | AR2: 41317 | AS2: 41318 | AT2: 41319 | AU2: 41320 | AV2: 41321 | AW2: 41322 | AX2: 41323 | AY2: 41324 | AZ2: 41325 | BA2: 41326 | BB2: 41327 | BC2: 41328 | BD2: 41329 | BE2: 41330 | BF2: 41331 | BG2: 41332 | BH2: 41333 | BI2: 41334 | BJ2: 41335 | BK2: 41336 | BL2: 41337 | BM2: 41338 | BN2: 41339 | BO2: 41340 | BP2: 41341 | BQ2: 41342 | BR2: 41343 | BS2: 41344 | BT2: 41345 | BU2: 41346 | BV2: 41347 | BW2: 41348 | BX2: 41349 | BY2: 41350 | BZ2: 41351 | CA2: 41352 | CB2: 41353 | CC2: 41354 | CD2: 41355 | CE2: 41356 | CF2: 41357 | CG2: 41358 | CH2: 41359 | CI2: 41360 | CJ2: 41361 | CK2: 41362 | CL2: 41363 | CM2: 41364 | CN2: 41365 | CO2: 41366 | CP2: 41367 | CQ2: 41368 | CR2: 41369 | CS2: 41370 | CT2: 41371 | CU2: 41372 | CV2: 41373 | CW2: 41374 | CX2: 41375 | CY2: 41376 | CZ2: 41377 | DA2: 41378 | DB2: 41379 | DC2: 41380 | DD2: 41381 | DE2: 41382 | DF2: 41383 | DG2: 41384 | DH2: 41385 | DI2: 41386 | DJ2: 41387 | DK2: 41388 | DL2: 41389 | DM2: 41390 | DN2: 41391 | DO2: 41392 | DP2: 41393 | DQ2: 41394 | DR2: 41395 | DS2: 41396 | DT2: 41397 | DU2: 41398 | DV2: 41399 | DW2: 41400 | DX2: 41401 | DY2: 41402 | DZ2: 41403 | EA2: 41404 | EB2: 41405 | EC2: 41406 | ED2: 41407 | EE2: 41408 | EF2: 41409 | EG2: 41410 | EH2: 41411 | EI2: 41412 | EJ2: 41413 | EK2: 41414 | EL2: 41415 | EM2: 41416 | EN2: 41417 | EO2: 41418 | EP2: 41419 | EQ2: 41420 | ER2: 41421 | ES2: 41422 | ET2: 41423 | EU2: 41424 | EV2: 41425 | EW2: 41426 | EX2: 41427 | EY2: 41428 | EZ2: 41429 | FA2: 41430 | FB2: 41431 | FC2: 41432 | FD2: 41433 | FE2: 41434 | FF2: 41435 | FG2: 41436 | FH2: 41437 | FI2: 41438 | FJ2: 41439 | FK2: 41440 | FL2: 41441 | FM2: 41442 | FN2: 41443 | FO2: 41444 | FP2: 41445 | FQ2: 41446 | FR2: 41447 | FS2: 41448 | FT2: 41449 | FU2: 41450 | FV2: 41451 | FW2: 41452 | FX2: 41453 | FY2: 41454 | FZ2: 41455 | GA2: 41456 | GB2: 41457 | GC2: 41458 | GD2: 41459 | GE2: 41460 | GF2: 41461 | GG2: 41462 | GH2: 41463 | GI2: 41464 | GJ2: 41465 | GK2: 41466 | GL2: 41467 | GM2: 41468 | GN2: 41469 | GO2: 41470 | GP2: 41471 | GQ2: 41472 | GR2: 41473 | GS2: 41474 | GT2: 41475 | GU2: 41476 | GV2: 41477 | GW2: 41478 | GX2: 41479 | GY2: 41480 | GZ2: 41481 | HA2: 41482 | HB2: 41483 | HC2: 41484 | HD2: 41485 | HE2: 41486 | HF2: 41487 | HG2: 41488 | HH2: 41489 | HI2: 41490 | HJ2: 41491 | HK2: 41492 | HL2: 41493 | HM2: 41494 | HN2: 41495 | HO2: 41496 | HP2: 41497 | HQ2: 41498 | HR2: 41499 | HS2: 41500 | HT2: 41501 | HU2: 41502 | HV2: 41503 | HW2: 41504 | HX2: 41505 | HY2: 41506 | HZ2: 41507 | IA2: 41508 | IB2: 41509 | IC2: 41510 | ID2: 41511 | IE2: 41512 | IF2: 41513 | IG2: 41514 | IH2: 41515 | II2: 41516 | IJ2: 41517 | IK2: 41518 | IL2: 41519 | IM2: 41520 | IN2: 41521 | IO2: 41522 | IP2: 41523 | IQ2: 41524 | IR2: 41525 | IS2: 41526 | IT2: 41527 | IU2: 41528 | IV2: 41529 | IW2: 41530 | IX2: 41531 | IY2: 41532 | IZ2: 41533 | JA2: 41534 | JB2: 41535 | JC2: 41536 | JD2: 41537 | JE2: 41538 | JF2: 41539 | JG2: 41540 | JH2: 41541 | JI2: 41542 | JJ2: 41543 | JK2: 41544 | JL2: 41545 | JM2: 41546 | JN2: 41547 | JO2: 41548 | JP2: 41549 | JQ2: 41550 | JR2: 41551 | JS2: 41552 | JT2: 41553 | JU2: 41554 | JV2: 41555 | JW2: 41556 | JX2: 41557 | JY2: 41558 | JZ2: 41559 | KA2: 41560 | KB2: 41561 | KC2: 41562 | KD2: 41563 | KE2: 41564 | KF2: 41565 | KG2: 41566 | KH2: 41567 | KI2: 41568 | KJ2: 41569 | KK2: 41570 | KL2: 41571 | KM2: 41572 | KN2: 41573 | KO2: 41574 | KP2: 41575 | KQ2: 41576 | KR2: 41577 | KS2: 41578 | KT2: 41579 | KU2: 41580 | KV2: 41581 | KW2: 41582 | KX2: 41583 | KY2: 41584 | KZ2: 41585 | LA2: 41586 | LB2: 41587 | LC2: 41588 | LD2: 41589 | LE2: 41590 | LF2: 41591 | LG2: 41592 | LH2: 41593 | LI2: 41594 | LJ2: 41595 | LK2: 41596 | LL2: 41597 | LM2: 41598 | LN2: 41599 | LO2: 41600 | LP2: 41601 | LQ2: 41602 | LR2: 41603 | LS2: 41604 | LT2: 41605 | LU2: 41606 | LV2: 41607 | LW2: 41608 | LX2: 41609 | LY2: 41610 | LZ2: 41611 | MA2: 41612 | MB2: 41613 | MC2: 41614 | MD2: 41615 | ME2: 41616 | MF2: 41617 | MG2: 41618 | MH2: 41619 | MI2: 41620 | MJ2: 41621 | MK2: 41622 | ML2: 41623 | MM2: 41624 | MN2: 41625 | MO2: 41626 | MP2: 41627 | MQ2: 41628 | MR2: 41629 | MS2: 41630 | MT2: 41631 | MU2: 41632 | MV2: 41633 | MW2: 41634 | MX2: 41635 | MY2: 41636 | MZ2: 41637 | NA2: 41638 | NB2: 41639 | NF2: Jan | NG2: Feb | NH2: Mar | NI2: Apr | NJ2: May | NK2: Jun | NL2: Jul | NM2: Aug | NN2: Sep | NO2: Oct | NP2: Nov | NQ2: Dec | NT2: Hourly Salary | NU2: Jan | NV2: Feb | NW2: Mar | NX2: Apr | NY2: May | NZ2: Jun | OA2: Jul | OB2: Aug | OC2: Sep | OD2: Oct | OE2: Nov | OF2: Dec
A3: D. Rahul | B3: 3 | C3: 2 | D3: 7 | E3: 4 | F3: 7 | G3: 4 | H3: 1 | I3: 6 | J3: 7 | K3: 4 | L3: 8 | M3: 0 | N3: 1 | O3: 0 | P3: 0 | Q3: 3 | R3: 5 | S3: 3 | T3: 3 | U3: 3 | V3: 5 | W3: 2 | X3: 2 | Y3: 3 | Z3: 0 | AA3: 4 | AB3: 2 | AC3: 6 | AD3: 4 | AE3: 6 | AF3: 6 | AG3: 4 | AH3: 8 | AI3: 8 | AJ3: 0 | AK3: 5 | AL3: 4 | AM3: 6 | AN3: 0 | AO3: 4 | AP3: 5 | AQ3: 4 | AR3: 3 | AS3: 1 | AT3: 7 | AU3: 2 | AV3: 5 | AW3: 3 | AX3: 8 | AY3: 4 | AZ3: 2 | BA3: 5 | BB3: 0 | BC3: 6 | BD3: 3 | BE3: 7 | BF3: 4 | BG3: 1 | BH3: 6 | BI3: 4 | BJ3: 3 | BK3: 8 | BL3: 4 | BM3: 3 | BN3: 4 | BO3: 2 | BP3: 1 | BQ3: 0 | BR3: 3 | BS3: 6 | BT3: 7 | BU3: 7 | BV3: 8 | BW3: 7 | BX3: 0 | BY3: 7 | BZ3: 5 | CA3: 2 | CB3: 3 | CC3: 8 | CD3: 5 | CE3: 5 | CF3: 1 | CG3: 8 | CH3: 8 | CI3: 1 | CJ3: 6 | CK3: 5 | CL3: 3 | CM3: 5 | CN3: 4 | CO3: 4 | CP3: 7 | CQ3: 2 | CR3: 8 | CS3: 5 | CT3: 2 | CU3: 3 | CV3: 3 | CW3: 4 | CX3: 6 | CY3: 6 | CZ3: 6 | DA3: 3 | DB3: 7 | DC3: 7 | DD3: 1 | DE3: 4 | DF3: 7 | DG3: 8 | DH3: 0 | DI3: 5 | DJ3: 0 | DK3: 6 | DL3: 7 | DM3: 7 | DN3: 8 | DO3: 1 | DP3: 2 | DQ3: 8 | DR3: 1 | DS3: 6 | DT3: 8 | DU3: 6 | DV3: 6 | DW3: 3 | DX3: 4 | DY3: 2 | DZ3: 8 | EA3: 3 | EB3: 4 | EC3: 4 | ED3: 1 | EE3: 1 | EF3: 3 | EG3: 5 | EH3: 5 | EI3: 8 | EJ3: 0 | EK3: 3 | EL3: 8 | EM3: 0 | EN3: 2 | EO3: 7 | EP3: 7 | EQ3: 7 | ER3: 3 | ES3: 0 | ET3: 0 | EU3: 0 | EV3: 4 | EW3: 3 | EX3: 0 | EY3: 6 | EZ3: 8 | FA3: 0 | FB3: 3 | FC3: 6 | FD3: 7 | FE3: 6 | FF3: 4 | FG3: 8 | FH3: 7 | FI3: 3 | FJ3: 6 | FK3: 5 | FL3: 2 | FM3: 5 | FN3: 2 | FO3: 1 | FP3: 4 | FQ3: 0 | FR3: 7 | FS3: 3 | FT3: 8 | FU3: 5 | FV3: 0 | FW3: 7 | FX3: 0 | FY3: 8 | FZ3: 0 | GA3: 7 | GB3: 6 | GC3: 4 | GD3: 3 | GE3: 6 | GF3: 8 | GG3: 3 | GH3: 2 | GI3: 3 | GJ3: 5 | GK3: 1 | GL3: 7 | GM3: 6 | GN3: 2 | GO3: 2 | GP3: 5 | GQ3: 6 | GR3: 5 | GS3: 3 | GT3: 5 | GU3: 2 | GV3: 2 | GW3: 7 | GX3: 7 | GY3: 7 | GZ3: 1 | HA3: 1 | HB3: 8 | HC3: 3 | HD3: 7 | HE3: 2 | HF3: 1 | HG3: 3 | HH3: 1 | HI3: 3 | HJ3: 7 | HK3: 6 | HL3: 1 | HM3: 8 | HN3: 0 | HO3: 4 | HP3: 6 | HQ3: 4 | HR3: 1 | HS3: 1 | HT3: 0 | HU3: 6 | HV3: 6 | HW3: 5 | HX3: 7 | HY3: 5 | HZ3: 8 | IA3: 0 | IB3: 8 | IC3: 1 | ID3: 8 | IE3: 1 | IF3: 7 | IG3: 1 | IH3: 3 | II3: 2 | IJ3: 2 | IK3: 0 | IL3: 1 | IM3: 6 | IN3: 5 | IO3: 6 | IP3: 2 | IQ3: 5 | IR3: 1 | IS3: 1 | IT3: 6 | IU3: 3 | IV3: 2 | IW3: 1 | IX3: 8 | IY3: 1 | IZ3: 7 | JA3: 2 | JB3: 6 | JC3: 3 | JD3: 2 | JE3: 5 | JF3: 4 | JG3: 2 | JH3: 2 | JI3: 4 | JJ3: 5 | JK3: 4 | JL3: 5 | JM3: 5 | JN3: 7 | JO3: 8 | JP3: 1 | JQ3: 2 | JR3: 3 | JS3: 4 | JT3: 5 | JU3: 6 | JV3: 4 | JW3: 4 | JX3: 3 | JY3: 6 | JZ3: 2 | KA3: 0 | KB3: 7 | KC3: 8 | KD3: 2 | KE3: 1 | KF3: 5 | KG3: 7 | KH3: 1 | KI3: 0 | KJ3: 6 | KK3: 3 | KL3: 2 | KM3: 7 | KN3: 5 | KO3: 8 | KP3: 6 | KQ3: 5 | KR3: 3 | KS3: 0 | KT3: 3 | KU3: 1 | KV3: 4 | KW3: 5 | KX3: 8 | KY3: 1 | KZ3: 3 | LA3: 5 | LB3: 2 | LC3: 3 | LD3: 0 | LE3: 8 | LF3: 4 | LG3: 6 | LH3: 3 | LI3: 6 | LJ3: 6 | LK3: 6 | LL3: 1 | LM3: 2 | LN3: 5 | LO3: 2 | LP3: 0 | LQ3: 6 | LR3: 6 | LS3: 8 | LT3: 7 | LU3: 4 | LV3: 2 | LW3: 1 | LX3: 7 | LY3: 0 | LZ3: 8 | MA3: 3 | MB3: 6 | MC3: 7 | MD3: 0 | ME3: 2 | MF3: 5 | MG3: 3 | MH3: 8 | MI3: 8 | MJ3: 5 | MK3: 1 | ML3: 2 | MM3: 3 | MN3: 8 | MO3: 2 | MP3: 4 | MQ3: 2 | MR3: 2 | MS3: 8 | MT3: 4 | MU3: 7 | MV3: 0 | MW3: 2 | MX3: 8 | MY3: 1 | MZ3: 1 | NA3: 7 | NB3: 6 | NE3: =A3 -> D. Rahul | NF3: =SUMIF($B$1:$NB$1,NF$1,$B3:$NB3) -> 111 | NG3: =SUMIF($B$1:$NB$1,NG$1,$B3:$NB3) -> 115 | NH3: =SUMIF($B$1:$NB$1,NH$1,$B3:$NB3) -> 139 | NI3: =SUMIF($B$1:$NB$1,NI$1,$B3:$NB3) -> 141 | NJ3: =SUMIF($B$1:$NB$1,NJ$1,$B3:$NB3) -> 119 | NK3: =SUMIF($B$1:$NB$1,NK$1,$B3:$NB3) -> 124 | NL3: =SUMIF($B$1:$NB$1,NL$1,$B3:$NB3) -> 136 | NM3: =SUMIF($B$1:$NB$1,NM$1,$B3:$NB3) -> 116 | ... NQ3: =SUMIF($B$1:$NB$1,NQ$1,$B3:$NB3) -> 130 | NS3: =NE3 -> D. Rahul | NT3: 100 | NU3: =$NT3*NF3 -> 11100 | NV3: =$NT3*NG3 -> 11500 | NW3: =$NT3*NH3 -> 13900 | NX3: =$NT3*NI3 -> 14100 | NY3: =$NT3*NJ3 -> 11900 | NZ3: =$NT3*NK3 -> 12400 | OA3: =$NT3*NL3 -> 13600 | OB3: =$NT3*NM3 -> 11600 | ... OF3: =$NT3*NQ3 -> 13000 | OH3: =IF(NS3="D.Rahul","YES","No") -> No
A4: M. Nisha | B4: 8 | C4: 2 | D4: 6 | E4: 0 | F4: 4 | G4: 5 | H4: 2 | I4: 6 | J4: 6 | K4: 2 | L4: 2 | M4: 8 | N4: 1 | O4: 2 | P4: 3 | Q4: 3 | R4: 0 | S4: 7 | T4: 0 | U4: 8 | V4: 3 | W4: 2 | X4: 3 | Y4: 1 | Z4: 4 | AA4: 8 | AB4: 0 | AC4: 1 | AD4: 6 | AE4: 4 | AF4: 4 | AG4: 0 | AH4: 7 | AI4: 7 | AJ4: 8 | AK4: 5 | AL4: 8 | AM4: 2 | AN4: 1 | AO4: 7 | AP4: 5 | AQ4: 5 | AR4: 6 | AS4: 0 | AT4: 5 | AU4: 1 | AV4: 4 | AW4: 4 | AX4: 7 | AY4: 5 | AZ4: 5 | BA4: 2 | BB4: 5 | BC4: 6 | BD4: 7 | BE4: 6 | BF4: 7 | BG4: 1 | BH4: 7 | BI4: 6 | BJ4: 1 | BK4: 2 | BL4: 5 | BM4: 8 | BN4: 5 | BO4: 5 | BP4: 5 | BQ4: 6 | BR4: 3 | BS4: 1 | BT4: 0 | BU4: 2 | BV4: 3 | BW4: 8 | BX4: 0 | BY4: 3 | BZ4: 3 | CA4: 5 | CB4: 2 | CC4: 2 | CD4: 2 | CE4: 7 | CF4: 4 | CG4: 1 | CH4: 3 | CI4: 2 | CJ4: 7 | CK4: 1 | CL4: 0 | CM4: 0 | CN4: 8 | CO4: 6 | CP4: 7 | CQ4: 1 | CR4: 3 | CS4: 2 | CT4: 0 | CU4: 3 | CV4: 0 | CW4: 7 | CX4: 8 | CY4: 1 | CZ4: 5 | DA4: 3 | DB4: 0 | DC4: 6 | DD4: 4 | DE4: 3 | DF4: 8 | DG4: 2 | DH4: 6 | DI4: 8 | DJ4: 5 | DK4: 5 | DL4: 1 | DM4: 3 | DN4: 5 | DO4: 6 | DP4: 1 | DQ4: 6 | DR4: 6 | DS4: 0 | DT4: 6 | DU4: 2 | DV4: 7 | DW4: 3 | DX4: 6 | DY4: 4 | DZ4: 0 | EA4: 0 | EB4: 8 | EC4: 4 | ED4: 7 | EE4: 4 | EF4: 1 | EG4: 0 | EH4: 3 | EI4: 3 | EJ4: 6 | EK4: 5 | EL4: 8 | EM4: 2 | EN4: 2 | EO4: 7 | EP4: 7 | EQ4: 5 | ER4: 7 | ES4: 5 | ET4: 1 | EU4: 7 | EV4: 1 | EW4: 1 | EX4: 3 | EY4: 6 | EZ4: 5 | FA4: 6 | FB4: 2 | FC4: 0 | FD4: 0 | FE4: 8 | FF4: 8 | FG4: 2 | FH4: 4 | FI4: 4 | FJ4: 0 | FK4: 6 | FL4: 4 | FM4: 7 | FN4: 6 | FO4: 2 | FP4: 5 | FQ4: 6 | FR4: 6 | FS4: 8 | FT4: 7 | FU4: 3 | FV4: 1 | FW4: 8 | FX4: 6 | FY4: 4 | FZ4: 7 | GA4: 5 | GB4: 5 | GC4: 0 | GD4: 3 | GE4: 0 | GF4: 5 | GG4: 8 | GH4: 7 | GI4: 2 | GJ4: 8 | GK4: 0 | GL4: 1 | GM4: 5 | GN4: 1 | GO4: 6 | GP4: 6 | GQ4: 3 | GR4: 1 | GS4: 7 | GT4: 6 | GU4: 3 | GV4: 5 | GW4: 8 | GX4: 5 | GY4: 4 | GZ4: 3 | HA4: 5 | HB4: 6 | HC4: 1 | HD4: 4 | HE4: 8 | HF4: 6 | HG4: 2 | HH4: 3 | HI4: 6 | HJ4: 4 | HK4: 4 | HL4: 3 | HM4: 5 | HN4: 8 | HO4: 6 | HP4: 6 | HQ4: 0 | HR4: 3 | HS4: 4 | HT4: 8 | HU4: 4 | HV4: 3 | HW4: 2 | HX4: 2 | HY4: 3 | HZ4: 6 | IA4: 4 | IB4: 1 | IC4: 7 | ID4: 1 | IE4: 1 | IF4: 0 | IG4: 6 | IH4: 4 | II4: 4 | IJ4: 7 | IK4: 2 | IL4: 2 | IM4: 0 | IN4: 7 | IO4: 1 | IP4: 5 | IQ4: 0 | IR4: 8 | IS4: 8 | IT4: 4 | IU4: 7 | IV4: 1 | IW4: 2 | IX4: 8 | IY4: 3 | IZ4: 0 | JA4: 8 | JB4: 0 | JC4: 2 | JD4: 0 | JE4: 0 | JF4: 4 | JG4: 5 | JH4: 6 | JI4: 4 | JJ4: 5 | JK4: 8 | JL4: 7 | JM4: 3 | JN4: 0 | JO4: 3 | JP4: 6 | JQ4: 0 | JR4: 3 | JS4: 6 | JT4: 8 | JU4: 7 | JV4: 1 | JW4: 8 | JX4: 8 | JY4: 0 | JZ4: 3 | KA4: 3 | KB4: 3 | KC4: 5 | KD4: 1 | KE4: 4 | KF4: 7 | KG4: 7 | KH4: 4 | KI4: 4 | KJ4: 0 | KK4: 1 | KL4: 0 | KM4: 7 | KN4: 3 | KO4: 3 | KP4: 6 | KQ4: 7 | KR4: 6 | KS4: 2 | KT4: 4 | KU4: 8 | KV4: 0 | KW4: 8 | KX4: 8 | KY4: 7 | KZ4: 6 | LA4: 2 | LB4: 4 | LC4: 8 | LD4: 5 | LE4: 0 | LF4: 2 | LG4: 2 | LH4: 6 | LI4: 4 | LJ4: 3 | LK4: 7 | LL4: 7 | LM4: 8 | LN4: 3 | LO4: 6 | LP4: 8 | LQ4: 0 | LR4: 3 | LS4: 6 | LT4: 5 | LU4: 1 | LV4: 4 | LW4: 1 | LX4: 6 | LY4: 5 | LZ4: 4 | MA4: 8 | MB4: 5 | MC4: 2 | MD4: 0 | ME4: 8 | MF4: 7 | MG4: 4 | MH4: 3 | MI4: 0 | MJ4: 1 | MK4: 2 | ML4: 7 | MM4: 1 | MN4: 3 | MO4: 7 | MP4: 5 | MQ4: 7 | MR4: 3 | MS4: 5 | MT4: 5 | MU4: 4 | MV4: 8 | MW4: 0 | MX4: 4 | MY4: 6 | MZ4: 1 | NA4: 7 | NB4: 3 | NE4: =A4 -> M. Nisha | NF4: =SUMIF($B$1:$NB$1,NF$1,$B4:$NB4) -> 111 | NG4: =SUMIF($B$1:$NB$1,NG$1,$B4:$NB4) -> 133 | NH4: =SUMIF($B$1:$NB$1,NH$1,$B4:$NB4) -> 102 | NI4: =SUMIF($B$1:$NB$1,NI$1,$B4:$NB4) -> 123 | NJ4: =SUMIF($B$1:$NB$1,NJ$1,$B4:$NB4) -> 127 | NK4: =SUMIF($B$1:$NB$1,NK$1,$B4:$NB4) -> 135 | NL4: =SUMIF($B$1:$NB$1,NL$1,$B4:$NB4) -> 131 | NM4: =SUMIF($B$1:$NB$1,NM$1,$B4:$NB4) -> 123 | ... NQ4: =SUMIF($B$1:$NB$1,NQ$1,$B4:$NB4) -> 131 | NS4: =NE4 -> M. Nisha | NT4: 75 | NU4: =$NT4*NF4 -> 8325 | NV4: =$NT4*NG4 -> 9975 | NW4: =$NT4*NH4 -> 7650 | NX4: =$NT4*NI4 -> 9225 | NY4: =$NT4*NJ4 -> 9525 | NZ4: =$NT4*NK4 -> 10125 | OA4: =$NT4*NL4 -> 9825 | OB4: =$NT4*NM4 -> 9225 | ... OF4: =$NT4*NQ4 -> 9825 | OH4: =IF(OF4>12000,"Above","Below") -> Below
A5: A. Anjali | B5: 7 | C5: 5 | D5: 0 | E5: 7 | F5: 1 | G5: 7 | H5: 1 | I5: 1 | J5: 0 | K5: 1 | L5: 0 | M5: 0 | N5: 7 | O5: 4 | P5: 8 | Q5: 6 | R5: 7 | S5: 8 | T5: 0 | U5: 6 | V5: 5 | W5: 4 | X5: 6 | Y5: 7 | Z5: 6 | AA5: 5 | AB5: 7 | AC5: 6 | AD5: 1 | AE5: 6 | AF5: 7 | AG5: 6 | AH5: 7 | AI5: 7 | AJ5: 7 | AK5: 2 | AL5: 1 | AM5: 8 | AN5: 5 | AO5: 8 | AP5: 5 | AQ5: 6 | AR5: 3 | AS5: 7 | AT5: 4 | AU5: 2 | AV5: 1 | AW5: 5 | AX5: 2 | AY5: 4 | AZ5: 5 | BA5: 5 | BB5: 7 | BC5: 7 | BD5: 4 | BE5: 6 | BF5: 0 | BG5: 6 | BH5: 4 | BI5: 1 | BJ5: 5 | BK5: 7 | BL5: 5 | BM5: 8 | BN5: 7 | BO5: 6 | BP5: 2 | BQ5: 7 | BR5: 3 | BS5: 3 | BT5: 8 | BU5: 0 | BV5: 6 | BW5: 8 | BX5: 3 | BY5: 2 | BZ5: 1 | CA5: 2 | CB5: 0 | CC5: 3 | CD5: 5 | CE5: 5 | CF5: 1 | CG5: 0 | CH5: 4 | CI5: 4 | CJ5: 2 | CK5: 2 | CL5: 6 | CM5: 3 | CN5: 3 | CO5: 8 | CP5: 3 | CQ5: 0 | CR5: 6 | CS5: 4 | CT5: 6 | CU5: 7 | CV5: 6 | CW5: 7 | CX5: 2 | CY5: 3 | CZ5: 3 | DA5: 0 | DB5: 0 | DC5: 0 | DD5: 3 | DE5: 8 | DF5: 0 | DG5: 0 | DH5: 6 | DI5: 1 | DJ5: 7 | DK5: 6 | DL5: 6 | DM5: 4 | DN5: 6 | DO5: 5 | DP5: 7 | DQ5: 4 | DR5: 4 | DS5: 1 | DT5: 2 | DU5: 3 | DV5: 4 | DW5: 8 | DX5: 7 | DY5: 3 | DZ5: 3 | EA5: 2 | EB5: 3 | EC5: 3 | ED5: 1 | EE5: 8 | EF5: 2 | EG5: 3 | EH5: 3 | EI5: 2 | EJ5: 2 | EK5: 3 | EL5: 3 | EM5: 3 | EN5: 1 | EO5: 6 | EP5: 0 | EQ5: 0 | ER5: 2 | ES5: 1 | ET5: 5 | EU5: 6 | EV5: 3 | EW5: 1 | EX5: 6 | EY5: 1 | EZ5: 2 | FA5: 3 | FB5: 3 | FC5: 1 | FD5: 7 | FE5: 1 | FF5: 2 | FG5: 1 | FH5: 4 | FI5: 5 | FJ5: 7 | FK5: 1 | FL5: 2 | FM5: 2 | FN5: 2 | FO5: 5 | FP5: 8 | FQ5: 7 | FR5: 2 | FS5: 5 | FT5: 5 | FU5: 6 | FV5: 7 | FW5: 7 | FX5: 0 | FY5: 1 | FZ5: 2 | GA5: 0 | GB5: 6 | GC5: 3 | GD5: 4 | GE5: 2 | GF5: 7 | GG5: 2 | GH5: 1 | GI5: 5 | GJ5: 7 | GK5: 7 | GL5: 4 | GM5: 3 | GN5: 1 | GO5: 2 | GP5: 2 | GQ5: 1 | GR5: 6 | GS5: 3 | GT5: 8 | GU5: 0 | GV5: 4 | GW5: 1 | GX5: 0 | GY5: 1 | GZ5: 7 | HA5: 7 | HB5: 3 | HC5: 2 | HD5: 1 | HE5: 8 | HF5: 3 | HG5: 1 | HH5: 8 | HI5: 2 | HJ5: 8 | HK5: 5 | HL5: 7 | HM5: 0 | HN5: 5 | HO5: 8 | HP5: 5 | HQ5: 0 | HR5: 7 | HS5: 0 | HT5: 4 | HU5: 5 | HV5: 5 | HW5: 4 | HX5: 0 | HY5: 4 | HZ5: 8 | IA5: 3 | IB5: 2 | IC5: 6 | ID5: 8 | IE5: 5 | IF5: 7 | IG5: 2 | IH5: 4 | II5: 4 | IJ5: 6 | IK5: 4 | IL5: 8 | IM5: 6 | IN5: 4 | IO5: 7 | IP5: 0 | IQ5: 5 | IR5: 8 | IS5: 7 | IT5: 0 | IU5: 3 | IV5: 3 | IW5: 1 | IX5: 7 | IY5: 3 | IZ5: 2 | JA5: 7 | JB5: 8 | JC5: 3 | JD5: 3 | JE5: 0 | JF5: 1 | JG5: 2 | JH5: 6 | JI5: 1 | JJ5: 2 | JK5: 8 | JL5: 8 | JM5: 0 | JN5: 4 | JO5: 7 | JP5: 1 | JQ5: 8 | JR5: 8 | JS5: 5 | JT5: 1 | JU5: 4 | JV5: 2 | JW5: 5 | JX5: 4 | JY5: 5 | JZ5: 0 | KA5: 7 | KB5: 8 | KC5: 7 | KD5: 6 | KE5: 4 | KF5: 4 | KG5: 3 | KH5: 8 | KI5: 8 | KJ5: 2 | KK5: 3 | KL5: 7 | KM5: 2 | KN5: 6 | KO5: 8 | KP5: 3 | KQ5: 0 | KR5: 6 | KS5: 7 | KT5: 6 | KU5: 0 | KV5: 3 | KW5: 0 | KX5: 0 | KY5: 3 | KZ5: 4 | LA5: 6 | LB5: 0 | LC5: 1 | LD5: 6 | LE5: 2 | LF5: 2 | LG5: 7 | LH5: 8 | LI5: 3 | LJ5: 2 | LK5: 4 | LL5: 2 | LM5: 8 | LN5: 4 | LO5: 6 | LP5: 8 | LQ5: 0 | LR5: 7 | LS5: 4 | LT5: 8 | LU5: 4 | LV5: 1 | LW5: 4 | LX5: 3 | LY5: 2 | LZ5: 0 | MA5: 6 | MB5: 5 | MC5: 6 | MD5: 7 | ME5: 1 | MF5: 3 | MG5: 0 | MH5: 2 | MI5: 5 | MJ5: 0 | MK5: 7 | ML5: 5 | MM5: 0 | MN5: 6 | MO5: 7 | MP5: 5 | MQ5: 7 | MR5: 5 | MS5: 8 | MT5: 8 | MU5: 1 | MV5: 8 | MW5: 5 | MX5: 5 | MY5: 0 | MZ5: 0 | NA5: 0 | NB5: 4 | NE5: =A5 -> A. Anjali | NF5: =SUMIF($B$1:$NB$1,NF$1,$B5:$NB5) -> 136 | NG5: =SUMIF($B$1:$NB$1,NG$1,$B5:$NB5) -> 134 | NH5: =SUMIF($B$1:$NB$1,NH$1,$B5:$NB5) -> 119 | NI5: =SUMIF($B$1:$NB$1,NI$1,$B5:$NB5) -> 121 | NJ5: =SUMIF($B$1:$NB$1,NJ$1,$B5:$NB5) -> 97 | NK5: =SUMIF($B$1:$NB$1,NK$1,$B5:$NB5) -> 106 | NL5: =SUMIF($B$1:$NB$1,NL$1,$B5:$NB5) -> 108 | NM5: =SUMIF($B$1:$NB$1,NM$1,$B5:$NB5) -> 136 | ... NQ5: =SUMIF($B$1:$NB$1,NQ$1,$B5:$NB5) -> 121 | NS5: =NE5 -> A. Anjali | NT5: 110 | NU5: =$NT5*NF5 -> 14960 | NV5: =$NT5*NG5 -> 14740 | NW5: =$NT5*NH5 -> 13090 | NX5: =$NT5*NI5 -> 13310 | NY5: =$NT5*NJ5 -> 10670 | NZ5: =$NT5*NK5 -> 11660 | OA5: =$NT5*NL5 -> 11880 | OB5: =$NT5*NM5 -> 14960 | ... OF5: =$NT5*NQ5 -> 13310 | OH5: =IF(OF5>12000,"Above","Below") -> Above
A6: S. Arjun | B6: 3 | C6: 5 | D6: 2 | E6: 4 | F6: 3 | G6: 3 | H6: 6 | I6: 2 | J6: 1 | K6: 3 | L6: 4 | M6: 4 | N6: 0 | O6: 6 | P6: 8 | Q6: 4 | R6: 5 | S6: 8 | T6: 0 | U6: 7 | V6: 7 | W6: 6 | X6: 0 | Y6: 5 | Z6: 5 | AA6: 6 | AB6: 5 | AC6: 8 | AD6: 2 | AE6: 1 | AF6: 7 | AG6: 4 | AH6: 0 | AI6: 6 | AJ6: 1 | AK6: 8 | AL6: 3 | AM6: 0 | AN6: 0 | AO6: 6 | AP6: 5 | AQ6: 0 | AR6: 7 | AS6: 1 | AT6: 8 | AU6: 4 | AV6: 3 | AW6: 4 | AX6: 0 | AY6: 6 | AZ6: 2 | BA6: 1 | BB6: 2 | BC6: 4 | BD6: 4 | BE6: 0 | BF6: 2 | BG6: 0 | BH6: 8 | BI6: 1 | BJ6: 7 | BK6: 6 | BL6: 7 | BM6: 6 | BN6: 6 | BO6: 5 | BP6: 5 | BQ6: 8 | BR6: 8 | BS6: 2 | BT6: 7 | BU6: 3 | BV6: 0 | BW6: 4 | BX6: 6 | BY6: 8 | BZ6: 8 | CA6: 4 | CB6: 0 | CC6: 2 | CD6: 0 | CE6: 4 | CF6: 5 | CG6: 7 | CH6: 0 | CI6: 0 | CJ6: 2 | CK6: 7 | CL6: 0 | CM6: 5 | CN6: 3 | CO6: 0 | CP6: 0 | CQ6: 0 | CR6: 6 | CS6: 4 | CT6: 6 | CU6: 8 | CV6: 6 | CW6: 8 | CX6: 5 | CY6: 8 | CZ6: 1 | DA6: 6 | DB6: 3 | DC6: 7 | DD6: 0 | DE6: 8 | DF6: 7 | DG6: 0 | DH6: 4 | DI6: 6 | DJ6: 4 | DK6: 5 | DL6: 5 | DM6: 0 | DN6: 7 | DO6: 1 | DP6: 7 | DQ6: 8 | DR6: 0 | DS6: 0 | DT6: 1 | DU6: 8 | DV6: 8 | DW6: 0 | DX6: 6 | DY6: 4 | DZ6: 8 | EA6: 2 | EB6: 4 | EC6: 7 | ED6: 4 | EE6: 4 | EF6: 6 | EG6: 5 | EH6: 5 | EI6: 5 | EJ6: 3 | EK6: 8 | EL6: 3 | EM6: 5 | EN6: 6 | EO6: 7 | EP6: 4 | EQ6: 2 | ER6: 5 | ES6: 1 | ET6: 6 | EU6: 3 | EV6: 6 | EW6: 0 | EX6: 7 | EY6: 0 | EZ6: 8 | FA6: 5 | FB6: 8 | FC6: 4 | FD6: 6 | FE6: 3 | FF6: 5 | FG6: 4 | FH6: 7 | FI6: 0 | FJ6: 3 | FK6: 5 | FL6: 8 | FM6: 1 | FN6: 2 | FO6: 0 | FP6: 4 | FQ6: 2 | FR6: 0 | FS6: 7 | FT6: 4 | FU6: 5 | FV6: 8 | FW6: 1 | FX6: 0 | FY6: 2 | FZ6: 2 | GA6: 5 | GB6: 7 | GC6: 8 | GD6: 3 | GE6: 4 | GF6: 2 | GG6: 3 | GH6: 6 | GI6: 4 | GJ6: 3 | GK6: 7 | GL6: 3 | GM6: 8 | GN6: 6 | GO6: 0 | GP6: 0 | GQ6: 8 | GR6: 1 | GS6: 8 | GT6: 6 | GU6: 7 | GV6: 1 | GW6: 6 | GX6: 4 | GY6: 0 | GZ6: 8 | HA6: 3 | HB6: 6 | HC6: 6 | HD6: 1 | HE6: 8 | HF6: 1 | HG6: 1 | HH6: 3 | HI6: 0 | HJ6: 5 | HK6: 6 | HL6: 7 | HM6: 7 | HN6: 6 | HO6: 3 | HP6: 4 | HQ6: 6 | HR6: 6 | HS6: 5 | HT6: 1 | HU6: 2 | HV6: 4 | HW6: 0 | HX6: 5 | HY6: 0 | HZ6: 2 | IA6: 2 | IB6: 3 | IC6: 8 | ID6: 4 | IE6: 4 | IF6: 4 | IG6: 1 | IH6: 0 | II6: 6 | IJ6: 6 | IK6: 3 | IL6: 7 | IM6: 6 | IN6: 6 | IO6: 0 | IP6: 1 | IQ6: 5 | IR6: 4 | IS6: 3 | IT6: 0 | IU6: 3 | IV6: 4 | IW6: 4 | IX6: 3 | IY6: 4 | IZ6: 4 | JA6: 0 | JB6: 5 | JC6: 2 | JD6: 3 | JE6: 3 | JF6: 7 | JG6: 8 | JH6: 5 | JI6: 3 | JJ6: 1 | JK6: 4 | JL6: 6 | JM6: 8 | JN6: 8 | JO6: 4 | JP6: 2 | JQ6: 0 | JR6: 7 | JS6: 0 | JT6: 2 | JU6: 7 | JV6: 2 | JW6: 8 | JX6: 7 | JY6: 4 | JZ6: 3 | KA6: 7 | KB6: 6 | KC6: 0 | KD6: 4 | KE6: 4 | KF6: 5 | KG6: 1 | KH6: 6 | KI6: 8 | KJ6: 2 | KK6: 7 | KL6: 0 | KM6: 3 | KN6: 3 | KO6: 0 | KP6: 3 | KQ6: 1 | KR6: 6 | KS6: 1 | KT6: 6 | KU6: 8 | KV6: 2 | KW6: 2 | KX6: 3 | KY6: 4 | KZ6: 6 | LA6: 6 | LB6: 8 | LC6: 6 | LD6: 6 | LE6: 6 | LF6: 4 | LG6: 2 | LH6: 5 | LI6: 2 | LJ6: 2 | LK6: 3 | LL6: 0 | LM6: 4 | LN6: 4 | LO6: 7 | LP6: 8 | LQ6: 2 | LR6: 3 | LS6: 0 | LT6: 7 | LU6: 7 | LV6: 5 | LW6: 0 | LX6: 0 | LY6: 0 | LZ6: 2 | MA6: 6 | MB6: 3 | MC6: 3 | MD6: 0 | ME6: 5 | MF6: 6 | MG6: 4 | MH6: 0 | MI6: 1 | MJ6: 2 | MK6: 6 | ML6: 4 | MM6: 5 | MN6: 3 | MO6: 1 | MP6: 1 | MQ6: 1 | MR6: 5 | MS6: 1 | MT6: 5 | MU6: 6 | MV6: 6 | MW6: 4 | MX6: 6 | MY6: 2 | MZ6: 2 | NA6: 2 | NB6: 2 | NE6: =A6 -> S. Arjun | NF6: =SUMIF($B$1:$NB$1,NF$1,$B6:$NB6) -> 130 | NG6: =SUMIF($B$1:$NB$1,NG$1,$B6:$NB6) -> 89 | NH6: =SUMIF($B$1:$NB$1,NH$1,$B6:$NB6) -> 133 | NI6: =SUMIF($B$1:$NB$1,NI$1,$B6:$NB6) -> 133 | NJ6: =SUMIF($B$1:$NB$1,NJ$1,$B6:$NB6) -> 136 | NK6: =SUMIF($B$1:$NB$1,NK$1,$B6:$NB6) -> 111 | NL6: =SUMIF($B$1:$NB$1,NL$1,$B6:$NB6) -> 142 | NM6: =SUMIF($B$1:$NB$1,NM$1,$B6:$NB6) -> 112 | ... NQ6: =SUMIF($B$1:$NB$1,NQ$1,$B6:$NB6) -> 94 | NS6: =NE6 -> S. Arjun | NT6: 60 | NU6: =$NT6*NF6 -> 7800 | NV6: =$NT6*NG6 -> 5340 | NW6: =$NT6*NH6 -> 7980 | NX6: =$NT6*NI6 -> 7980 | NY6: =$NT6*NJ6 -> 8160 | NZ6: =$NT6*NK6 -> 6660 | OA6: =$NT6*NL6 -> 8520 | OB6: =$NT6*NM6 -> 6720 | ... OF6: =$NT6*NQ6 -> 5640 | OH6: =IF(OF6>12000,"Above","Below") -> Below
A7: T. Sachin | B7: 8 | C7: 7 | D7: 3 | E7: 1 | F7: 7 | G7: 6 | H7: 3 | I7: 7 | J7: 4 | K7: 3 | L7: 2 | M7: 4 | N7: 5 | O7: 4 | P7: 3 | Q7: 4 | R7: 4 | S7: 5 | T7: 1 | U7: 4 | V7: 6 | W7: 4 | X7: 1 | Y7: 3 | Z7: 7 | AA7: 3 | AB7: 7 | AC7: 4 | AD7: 5 | AE7: 2 | AF7: 5 | AG7: 8 | AH7: 8 | AI7: 7 | AJ7: 6 | AK7: 2 | AL7: 3 | AM7: 6 | AN7: 3 | AO7: 0 | AP7: 2 | AQ7: 5 | AR7: 4 | AS7: 5 | AT7: 1 | AU7: 0 | AV7: 0 | AW7: 0 | AX7: 5 | AY7: 8 | AZ7: 3 | BA7: 8 | BB7: 0 | BC7: 7 | BD7: 5 | BE7: 3 | BF7: 3 | BG7: 4 | BH7: 8 | BI7: 3 | BJ7: 1 | BK7: 2 | BL7: 8 | BM7: 2 | BN7: 1 | BO7: 6 | BP7: 4 | BQ7: 6 | BR7: 8 | BS7: 0 | BT7: 8 | BU7: 0 | BV7: 1 | BW7: 0 | BX7: 3 | BY7: 1 | BZ7: 8 | CA7: 1 | CB7: 2 | CC7: 1 | CD7: 3 | CE7: 1 | CF7: 6 | CG7: 1 | CH7: 7 | CI7: 5 | CJ7: 6 | CK7: 2 | CL7: 5 | CM7: 0 | CN7: 0 | CO7: 8 | CP7: 5 | CQ7: 0 | CR7: 7 | CS7: 2 | CT7: 8 | CU7: 1 | CV7: 2 | CW7: 2 | CX7: 6 | CY7: 4 | CZ7: 1 | DA7: 1 | DB7: 8 | DC7: 3 | DD7: 5 | DE7: 1 | DF7: 6 | DG7: 2 | DH7: 4 | DI7: 8 | DJ7: 6 | DK7: 8 | DL7: 0 | DM7: 2 | DN7: 7 | DO7: 7 | DP7: 0 | DQ7: 0 | DR7: 5 | DS7: 5 | DT7: 0 | DU7: 6 | DV7: 5 | DW7: 1 | DX7: 5 | DY7: 1 | DZ7: 6 | EA7: 7 | EB7: 2 | EC7: 2 | ED7: 2 | EE7: 1 | EF7: 4 | EG7: 6 | EH7: 2 | EI7: 6 | EJ7: 6 | EK7: 1 | EL7: 8 | EM7: 1 | EN7: 3 | EO7: 8 | EP7: 2 | EQ7: 3 | ER7: 1 | ES7: 4 | ET7: 4 | EU7: 4 | EV7: 6 | EW7: 1 | EX7: 1 | EY7: 8 | EZ7: 0 | FA7: 4 | FB7: 4 | FC7: 3 | FD7: 6 | FE7: 5 | FF7: 6 | FG7: 7 | FH7: 3 | FI7: 6 | FJ7: 1 | FK7: 5 | FL7: 4 | FM7: 8 | FN7: 4 | FO7: 6 | FP7: 4 | FQ7: 6 | FR7: 1 | FS7: 3 | FT7: 0 | FU7: 7 | FV7: 1 | FW7: 5 | FX7: 8 | FY7: 7 | FZ7: 4 | GA7: 2 | GB7: 3 | GC7: 8 | GD7: 0 | GE7: 3 | GF7: 6 | GG7: 2 | GH7: 3 | GI7: 7 | GJ7: 7 | GK7: 8 | GL7: 3 | GM7: 1 | GN7: 5 | GO7: 5 | GP7: 0 | GQ7: 1 | GR7: 5 | GS7: 7 | GT7: 2 | GU7: 3 | GV7: 8 | GW7: 4 | GX7: 4 | GY7: 1 | GZ7: 2 | HA7: 5 | HB7: 1 | HC7: 3 | HD7: 7 | HE7: 5 | HF7: 6 | HG7: 6 | HH7: 1 | HI7: 4 | HJ7: 1 | HK7: 8 | HL7: 5 | HM7: 3 | HN7: 3 | HO7: 3 | HP7: 4 | HQ7: 2 | HR7: 3 | HS7: 5 | HT7: 3 | HU7: 3 | HV7: 1 | HW7: 2 | HX7: 2 | HY7: 8 | HZ7: 0 | IA7: 3 | IB7: 2 | IC7: 6 | ID7: 7 | IE7: 8 | IF7: 1 | IG7: 1 | IH7: 1 | II7: 4 | IJ7: 5 | IK7: 7 | IL7: 2 | IM7: 2 | IN7: 0 | IO7: 1 | IP7: 1 | IQ7: 7 | IR7: 2 | IS7: 0 | IT7: 6 | IU7: 2 | IV7: 3 | IW7: 6 | IX7: 3 | IY7: 5 | IZ7: 1 | JA7: 6 | JB7: 2 | JC7: 4 | JD7: 0 | JE7: 5 | JF7: 8 | JG7: 8 | JH7: 0 | JI7: 6 | JJ7: 3 | JK7: 6 | JL7: 7 | JM7: 4 | JN7: 8 | JO7: 8 | JP7: 3 | JQ7: 0 | JR7: 7 | JS7: 5 | JT7: 2 | JU7: 0 | JV7: 5 | JW7: 2 | JX7: 6 | JY7: 2 | JZ7: 6 | KA7: 3 | KB7: 1 | KC7: 2 | KD7: 1 | KE7: 3 | KF7: 8 | KG7: 7 | KH7: 2 | KI7: 4 | KJ7: 2 | KK7: 0 | KL7: 3 | KM7: 5 | KN7: 5 | KO7: 2 | KP7: 1 | KQ7: 8 | KR7: 5 | KS7: 2 | KT7: 5 | KU7: 3 | KV7: 7 | KW7: 1 | KX7: 8 | KY7: 6 | KZ7: 4 | LA7: 4 | LB7: 4 | LC7: 7 | LD7: 0 | LE7: 8 | LF7: 7 | LG7: 6 | LH7: 1 | LI7: 6 | LJ7: 4 | LK7: 1 | LL7: 7 | LM7: 7 | LN7: 2 | LO7: 0 | LP7: 3 | LQ7: 5 | LR7: 5 | LS7: 4 | LT7: 5 | LU7: 5 | LV7: 4 | LW7: 8 | LX7: 1 | LY7: 2 | LZ7: 6 | MA7: 8 | MB7: 5 | MC7: 8 | MD7: 4 | ME7: 0 | MF7: 3 | MG7: 4 | MH7: 8 | MI7: 8 | MJ7: 4 | MK7: 3 | ML7: 6 | MM7: 8 | MN7: 2 | MO7: 8 | MP7: 1 | MQ7: 0 | MR7: 2 | MS7: 5 | MT7: 4 | MU7: 5 | MV7: 5 | MW7: 5 | MX7: 4 | MY7: 1 | MZ7: 3 | NA7: 8 | NB7: 5 | NE7: =A7 -> T. Sachin | NF7: =SUMIF($B$1:$NB$1,NF$1,$B7:$NB7) -> 132 | NG7: =SUMIF($B$1:$NB$1,NG$1,$B7:$NB7) -> 114 | NH7: =SUMIF($B$1:$NB$1,NH$1,$B7:$NB7) -> 102 | NI7: =SUMIF($B$1:$NB$1,NI$1,$B7:$NB7) -> 114 | NJ7: =SUMIF($B$1:$NB$1,NJ$1,$B7:$NB7) -> 117 | NK7: =SUMIF($B$1:$NB$1,NK$1,$B7:$NB7) -> 128 | NL7: =SUMIF($B$1:$NB$1,NL$1,$B7:$NB7) -> 121 | NM7: =SUMIF($B$1:$NB$1,NM$1,$B7:$NB7) -> 111 | ... NQ7: =SUMIF($B$1:$NB$1,NQ$1,$B7:$NB7) -> 136 | NS7: =NE7 -> T. Sachin | NT7: 70 | NU7: =$NT7*NF7 -> 9240 | NV7: =$NT7*NG7 -> 7980 | NW7: =$NT7*NH7 -> 7140 | NX7: =$NT7*NI7 -> 7980 | NY7: =$NT7*NJ7 -> 8190 | NZ7: =$NT7*NK7 -> 8960 | OA7: =$NT7*NL7 -> 8470 | OB7: =$NT7*NM7 -> 7770 | ... OF7: =$NT7*NQ7 -> 9520 | OH7: =IF(OF7>12000,"Above","Below") -> Below
A8: K. Ahmed | B8: 8 | C8: 4 | D8: 6 | E8: 7 | F8: 1 | G8: 8 | H8: 2 | I8: 7 | J8: 2 | K8: 6 | L8: 5 | M8: 0 | N8: 5 | O8: 4 | P8: 2 | Q8: 7 | R8: 4 | S8: 3 | T8: 1 | U8: 6 | V8: 1 | W8: 8 | X8: 1 | Y8: 7 | Z8: 7 | AA8: 6 | AB8: 2 | AC8: 3 | AD8: 2 | AE8: 4 | AF8: 4 | AG8: 8 | AH8: 0 | AI8: 8 | AJ8: 7 | AK8: 6 | AL8: 7 | AM8: 8 | AN8: 0 | AO8: 3 | AP8: 7 | AQ8: 1 | AR8: 3 | AS8: 5 | AT8: 4 | AU8: 6 | AV8: 7 | AW8: 8 | AX8: 5 | AY8: 2 | AZ8: 6 | BA8: 4 | BB8: 0 | BC8: 0 | BD8: 1 | BE8: 4 | BF8: 1 | BG8: 1 | BH8: 7 | BI8: 0 | BJ8: 7 | BK8: 2 | BL8: 0 | BM8: 0 | BN8: 0 | BO8: 7 | BP8: 5 | BQ8: 0 | BR8: 1 | BS8: 3 | BT8: 3 | BU8: 3 | BV8: 8 | BW8: 7 | BX8: 0 | BY8: 0 | BZ8: 4 | CA8: 8 | CB8: 0 | CC8: 3 | CD8: 8 | CE8: 8 | CF8: 0 | CG8: 6 | CH8: 4 | CI8: 8 | CJ8: 0 | CK8: 7 | CL8: 2 | CM8: 6 | CN8: 3 | CO8: 5 | CP8: 1 | CQ8: 7 | CR8: 7 | CS8: 1 | CT8: 1 | CU8: 7 | CV8: 7 | CW8: 6 | CX8: 5 | CY8: 3 | CZ8: 8 | DA8: 0 | DB8: 3 | DC8: 4 | DD8: 0 | DE8: 5 | DF8: 1 | DG8: 3 | DH8: 1 | DI8: 7 | DJ8: 8 | DK8: 4 | DL8: 2 | DM8: 0 | DN8: 5 | DO8: 0 | DP8: 7 | DQ8: 4 | DR8: 8 | DS8: 6 | DT8: 8 | DU8: 1 | DV8: 4 | DW8: 0 | DX8: 0 | DY8: 0 | DZ8: 5 | EA8: 6 | EB8: 3 | EC8: 0 | ED8: 3 | EE8: 5 | EF8: 5 | EG8: 0 | EH8: 7 | EI8: 3 | EJ8: 0 | EK8: 6 | EL8: 8 | EM8: 3 | EN8: 5 | EO8: 5 | EP8: 0 | EQ8: 5 | ER8: 8 | ES8: 6 | ET8: 4 | EU8: 4 | EV8: 8 | EW8: 1 | EX8: 4 | EY8: 1 | EZ8: 7 | FA8: 0 | FB8: 7 | FC8: 6 | FD8: 1 | FE8: 2 | FF8: 8 | FG8: 0 | FH8: 5 | FI8: 5 | FJ8: 3 | FK8: 5 | FL8: 2 | FM8: 1 | FN8: 7 | FO8: 6 | FP8: 6 | FQ8: 5 | FR8: 4 | FS8: 3 | FT8: 2 | FU8: 4 | FV8: 6 | FW8: 6 | FX8: 5 | FY8: 8 | FZ8: 6 | GA8: 0 | GB8: 5 | GC8: 5 | GD8: 3 | GE8: 7 | GF8: 1 | GG8: 6 | GH8: 6 | GI8: 3 | GJ8: 4 | GK8: 5 | GL8: 8 | GM8: 1 | GN8: 5 | GO8: 8 | GP8: 8 | GQ8: 8 | GR8: 0 | GS8: 2 | GT8: 1 | GU8: 8 | GV8: 3 | GW8: 8 | GX8: 1 | GY8: 7 | GZ8: 6 | HA8: 6 | HB8: 3 | HC8: 7 | HD8: 8 | HE8: 8 | HF8: 4 | HG8: 7 | HH8: 2 | HI8: 7 | HJ8: 0 | HK8: 4 | HL8: 0 | HM8: 0 | HN8: 7 | HO8: 5 | HP8: 3 | HQ8: 2 | HR8: 4 | HS8: 1 | HT8: 0 | HU8: 2 | HV8: 5 | HW8: 5 | HX8: 5 | HY8: 6 | HZ8: 5 | IA8: 8 | IB8: 2 | IC8: 4 | ID8: 2 | IE8: 4 | IF8: 7 | IG8: 8 | IH8: 3 | II8: 8 | IJ8: 7 | IK8: 4 | IL8: 0 | IM8: 3 | IN8: 8 | IO8: 3 | IP8: 3 | IQ8: 1 | IR8: 2 | IS8: 0 | IT8: 7 | IU8: 2 | IV8: 2 | IW8: 6 | IX8: 1 | IY8: 3 | IZ8: 5 | JA8: 8 | JB8: 5 | JC8: 6 | JD8: 8 | JE8: 2 | JF8: 6 | JG8: 5 | JH8: 1 | JI8: 7 | JJ8: 1 | JK8: 6 | JL8: 7 | JM8: 5 | JN8: 2 | JO8: 3 | JP8: 3 | JQ8: 0 | JR8: 8 | JS8: 3 | JT8: 6 | JU8: 2 | JV8: 6 | JW8: 4 | JX8: 0 | JY8: 1 | JZ8: 5 | KA8: 5 | KB8: 3 | KC8: 7 | KD8: 3 | KE8: 2 | KF8: 7 | KG8: 1 | KH8: 4 | KI8: 3 | KJ8: 5 | KK8: 6 | KL8: 8 | KM8: 0 | KN8: 5 | KO8: 7 | KP8: 0 | KQ8: 4 | KR8: 7 | KS8: 1 | KT8: 5 | KU8: 2 | KV8: 0 | KW8: 6 | KX8: 8 | KY8: 5 | KZ8: 0 | LA8: 7 | LB8: 5 | LC8: 5 | LD8: 7 | LE8: 0 | LF8: 5 | LG8: 5 | LH8: 8 | LI8: 8 | LJ8: 2 | LK8: 5 | LL8: 4 | LM8: 1 | LN8: 4 | LO8: 5 | LP8: 7 | LQ8: 3 | LR8: 0 | LS8: 0 | LT8: 7 | LU8: 6 | LV8: 5 | LW8: 7 | LX8: 1 | LY8: 1 | LZ8: 3 | MA8: 1 | MB8: 5 | MC8: 3 | MD8: 6 | ME8: 5 | MF8: 4 | MG8: 6 | MH8: 7 | MI8: 6 | MJ8: 3 | MK8: 1 | ML8: 6 | MM8: 7 | MN8: 0 | MO8: 1 | MP8: 2 | MQ8: 0 | MR8: 8 | MS8: 1 | MT8: 5 | MU8: 0 | MV8: 8 | MW8: 0 | MX8: 2 | MY8: 4 | MZ8: 5 | NA8: 1 | NB8: 6 | NE8: =A8 -> K. Ahmed | NF8: =SUMIF($B$1:$NB$1,NF$1,$B8:$NB8) -> 133 | NG8: =SUMIF($B$1:$NB$1,NG$1,$B8:$NB8) -> 119 | NH8: =SUMIF($B$1:$NB$1,NH$1,$B8:$NB8) -> 110 | NI8: =SUMIF($B$1:$NB$1,NI$1,$B8:$NB8) -> 115 | NJ8: =SUMIF($B$1:$NB$1,NJ$1,$B8:$NB8) -> 126 | NK8: =SUMIF($B$1:$NB$1,NK$1,$B8:$NB8) -> 126 | NL8: =SUMIF($B$1:$NB$1,NL$1,$B8:$NB8) -> 151 | NM8: =SUMIF($B$1:$NB$1,NM$1,$B8:$NB8) -> 127 | ... NQ8: =SUMIF($B$1:$NB$1,NQ$1,$B8:$NB8) -> 108 | NS8: =NE8 -> K. Ahmed | NT8: 60 | NU8: =$NT8*NF8 -> 7980 | NV8: =$NT8*NG8 -> 7140 | NW8: =$NT8*NH8 -> 6600 | NX8: =$NT8*NI8 -> 6900 | NY8: =$NT8*NJ8 -> 7560 | NZ8: =$NT8*NK8 -> 7560 | OA8: =$NT8*NL8 -> 9060 | OB8: =$NT8*NM8 -> 7620 | ... OF8: =$NT8*NQ8 -> 6480 | OH8: =IF(OF8>12000,"Above","Below") -> Below
A9: N. Khan | B9: 3 | C9: 2 | D9: 8 | E9: 2 | F9: 0 | G9: 3 | H9: 1 | I9: 6 | J9: 6 | K9: 3 | L9: 4 | M9: 1 | N9: 4 | O9: 2 | P9: 1 | Q9: 2 | R9: 6 | S9: 4 | T9: 0 | U9: 6 | V9: 4 | W9: 4 | X9: 7 | Y9: 3 | Z9: 5 | AA9: 8 | AB9: 4 | AC9: 5 | AD9: 4 | AE9: 8 | AF9: 5 | AG9: 6 | AH9: 0 | AI9: 3 | AJ9: 3 | AK9: 5 | AL9: 2 | AM9: 6 | AN9: 8 | AO9: 2 | AP9: 1 | AQ9: 4 | AR9: 6 | AS9: 7 | AT9: 7 | AU9: 8 | AV9: 7 | AW9: 5 | AX9: 1 | AY9: 4 | AZ9: 7 | BA9: 3 | BB9: 0 | BC9: 6 | BD9: 0 | BE9: 4 | BF9: 2 | BG9: 7 | BH9: 5 | BI9: 5 | BJ9: 7 | BK9: 6 | BL9: 6 | BM9: 3 | BN9: 3 | BO9: 2 | BP9: 7 | BQ9: 6 | BR9: 5 | BS9: 2 | BT9: 3 | BU9: 3 | BV9: 0 | BW9: 8 | BX9: 0 | BY9: 0 | BZ9: 7 | CA9: 0 | CB9: 3 | CC9: 2 | CD9: 3 | CE9: 4 | CF9: 6 | CG9: 6 | CH9: 7 | CI9: 7 | CJ9: 3 | CK9: 3 | CL9: 4 | CM9: 5 | CN9: 7 | CO9: 3 | CP9: 5 | CQ9: 7 | CR9: 0 | CS9: 0 | CT9: 0 | CU9: 4 | CV9: 5 | CW9: 0 | CX9: 6 | CY9: 7 | CZ9: 4 | DA9: 1 | DB9: 2 | DC9: 1 | DD9: 4 | DE9: 0 | DF9: 5 | DG9: 3 | DH9: 7 | DI9: 5 | DJ9: 5 | DK9: 5 | DL9: 8 | DM9: 4 | DN9: 7 | DO9: 2 | DP9: 1 | DQ9: 6 | DR9: 5 | DS9: 8 | DT9: 7 | DU9: 1 | DV9: 7 | DW9: 6 | DX9: 3 | DY9: 8 | DZ9: 7 | EA9: 5 | EB9: 8 | EC9: 4 | ED9: 1 | EE9: 8 | EF9: 8 | EG9: 0 | EH9: 4 | EI9: 8 | EJ9: 7 | EK9: 1 | EL9: 5 | EM9: 7 | EN9: 7 | EO9: 2 | EP9: 6 | EQ9: 5 | ER9: 1 | ES9: 8 | ET9: 2 | EU9: 4 | EV9: 5 | EW9: 3 | EX9: 5 | EY9: 4 | EZ9: 7 | FA9: 6 | FB9: 4 | FC9: 4 | FD9: 2 | FE9: 1 | FF9: 3 | FG9: 6 | FH9: 8 | FI9: 8 | FJ9: 6 | FK9: 2 | FL9: 6 | FM9: 3 | FN9: 6 | FO9: 3 | FP9: 6 | FQ9: 2 | FR9: 4 | FS9: 3 | FT9: 4 | FU9: 4 | FV9: 1 | FW9: 1 | FX9: 8 | FY9: 4 | FZ9: 3 | GA9: 4 | GB9: 3 | GC9: 2 | GD9: 3 | GE9: 6 | GF9: 0 | GG9: 3 | GH9: 1 | GI9: 7 | GJ9: 0 | GK9: 7 | GL9: 6 | GM9: 6 | GN9: 6 | GO9: 7 | GP9: 1 | GQ9: 7 | GR9: 2 | GS9: 8 | GT9: 6 | GU9: 8 | GV9: 1 | GW9: 6 | GX9: 6 | GY9: 4 | GZ9: 3 | HA9: 8 | HB9: 0 | HC9: 8 | HD9: 1 | HE9: 6 | HF9: 7 | HG9: 6 | HH9: 2 | HI9: 6 | HJ9: 0 | HK9: 3 | HL9: 7 | HM9: 1 | HN9: 8 | HO9: 7 | HP9: 1 | HQ9: 6 | HR9: 4 | HS9: 6 | HT9: 8 | HU9: 2 | HV9: 7 | HW9: 6 | HX9: 6 | HY9: 7 | HZ9: 8 | IA9: 6 | IB9: 5 | IC9: 2 | ID9: 2 | IE9: 4 | IF9: 6 | IG9: 2 | IH9: 1 | II9: 1 | IJ9: 3 | IK9: 2 | IL9: 1 | IM9: 2 | IN9: 1 | IO9: 0 | IP9: 6 | IQ9: 6 | IR9: 6 | IS9: 6 | IT9: 3 | IU9: 4 | IV9: 3 | IW9: 0 | IX9: 3 | IY9: 3 | IZ9: 0 | JA9: 2 | JB9: 2 | JC9: 8 | JD9: 0 | JE9: 6 | JF9: 2 | JG9: 3 | JH9: 4 | JI9: 6 | JJ9: 2 | JK9: 8 | JL9: 7 | JM9: 3 | JN9: 1 | JO9: 0 | JP9: 0 | JQ9: 4 | JR9: 2 | JS9: 3 | JT9: 2 | JU9: 4 | JV9: 4 | JW9: 1 | JX9: 2 | JY9: 4 | JZ9: 8 | KA9: 2 | KB9: 6 | KC9: 5 | KD9: 0 | KE9: 2 | KF9: 3 | KG9: 6 | KH9: 1 | KI9: 4 | KJ9: 6 | KK9: 6 | KL9: 8 | KM9: 7 | KN9: 8 | KO9: 6 | KP9: 4 | KQ9: 3 | KR9: 1 | KS9: 5 | KT9: 0 | KU9: 8 | KV9: 3 | KW9: 0 | KX9: 0 | KY9: 0 | KZ9: 5 | LA9: 8 | LB9: 4 | LC9: 0 | LD9: 6 | LE9: 3 | LF9: 7 | LG9: 8 | LH9: 1 | LI9: 5 | LJ9: 5 | LK9: 4 | LL9: 1 | LM9: 8 | LN9: 6 | LO9: 4 | LP9: 5 | LQ9: 4 | LR9: 1 | LS9: 0 | LT9: 8 | LU9: 0 | LV9: 2 | LW9: 6 | LX9: 6 | LY9: 8 | LZ9: 3 | MA9: 8 | MB9: 4 | MC9: 1 | MD9: 8 | ME9: 6 | MF9: 5 | MG9: 5 | MH9: 8 | MI9: 0 | MJ9: 0 | MK9: 3 | ML9: 5 | MM9: 8 | MN9: 5 | MO9: 1 | MP9: 7 | MQ9: 6 | MR9: 0 | MS9: 2 | MT9: 4 | MU9: 5 | MV9: 2 | MW9: 8 | MX9: 7 | MY9: 3 | MZ9: 3 | NA9: 8 | NB9: 7 | NE9: =A9 -> N. Khan | NF9: =SUMIF($B$1:$NB$1,NF$1,$B9:$NB9) -> 121 | NG9: =SUMIF($B$1:$NB$1,NG$1,$B9:$NB9) -> 119 | NH9: =SUMIF($B$1:$NB$1,NH$1,$B9:$NB9) -> 126 | NI9: =SUMIF($B$1:$NB$1,NI$1,$B9:$NB9) -> 114 | NJ9: =SUMIF($B$1:$NB$1,NJ$1,$B9:$NB9) -> 158 | NK9: =SUMIF($B$1:$NB$1,NK$1,$B9:$NB9) -> 127 | NL9: =SUMIF($B$1:$NB$1,NL$1,$B9:$NB9) -> 136 | NM9: =SUMIF($B$1:$NB$1,NM$1,$B9:$NB9) -> 140 | ... NQ9: =SUMIF($B$1:$NB$1,NQ$1,$B9:$NB9) -> 146 | NS9: =NE9 -> N. Khan | NT9: 70 | NU9: =$NT9*NF9 -> 8470 | NV9: =$NT9*NG9 -> 8330 | NW9: =$NT9*NH9 -> 8820 | NX9: =$NT9*NI9 -> 7980 | NY9: =$NT9*NJ9 -> 11060 | NZ9: =$NT9*NK9 -> 8890 | OA9: =$NT9*NL9 -> 9520 | OB9: =$NT9*NM9 -> 9800 | ... OF9: =$NT9*NQ9 -> 10220 | OH9: =IF(OF9>12000,"Above","Below") -> Below
A10: G. Michael | B10: 3 | C10: 1 | D10: 7 | E10: 4 | F10: 0 | G10: 3 | H10: 7 | I10: 7 | J10: 7 | K10: 0 | L10: 0 | M10: 4 | N10: 1 | O10: 6 | P10: 6 | Q10: 5 | R10: 7 | S10: 2 | T10: 1 | U10: 0 | V10: 6 | W10: 5 | X10: 8 | Y10: 6 | Z10: 5 | AA10: 1 | AB10: 7 | AC10: 3 | AD10: 1 | AE10: 0 | AF10: 4 | AG10: 0 | AH10: 3 | AI10: 6 | AJ10: 6 | AK10: 6 | AL10: 5 | AM10: 5 | AN10: 8 | AO10: 7 | AP10: 1 | AQ10: 3 | AR10: 5 | AS10: 0 | AT10: 2 | AU10: 7 | AV10: 8 | AW10: 2 | AX10: 2 | AY10: 2 | AZ10: 2 | BA10: 4 | BB10: 1 | BC10: 7 | BD10: 6 | BE10: 5 | BF10: 6 | BG10: 7 | BH10: 0 | BI10: 3 | BJ10: 1 | BK10: 5 | BL10: 4 | BM10: 5 | BN10: 2 | BO10: 8 | BP10: 8 | BQ10: 5 | BR10: 2 | BS10: 0 | BT10: 3 | BU10: 2 | BV10: 5 | BW10: 2 | BX10: 4 | BY10: 0 | BZ10: 5 | CA10: 5 | CB10: 0 | CC10: 3 | CD10: 1 | CE10: 7 | CF10: 2 | CG10: 5 | CH10: 6 | CI10: 7 | CJ10: 8 | CK10: 3 | CL10: 2 | CM10: 2 | CN10: 1 | CO10: 5 | CP10: 5 | CQ10: 6 | CR10: 0 | CS10: 4 | CT10: 1 | CU10: 1 | CV10: 4 | CW10: 4 | CX10: 7 | CY10: 5 | CZ10: 0 | DA10: 2 | DB10: 7 | DC10: 7 | DD10: 7 | DE10: 0 | DF10: 7 | DG10: 6 | DH10: 8 | DI10: 4 | DJ10: 6 | DK10: 6 | DL10: 1 | DM10: 8 | DN10: 8 | DO10: 1 | DP10: 0 | DQ10: 4 | DR10: 7 | DS10: 6 | DT10: 5 | DU10: 7 | DV10: 1 | DW10: 8 | DX10: 7 | DY10: 5 | DZ10: 4 | EA10: 6 | EB10: 8 | EC10: 1 | ED10: 1 | EE10: 0 | EF10: 8 | EG10: 0 | EH10: 1 | EI10: 7 | EJ10: 0 | EK10: 3 | EL10: 3 | EM10: 7 | EN10: 8 | EO10: 5 | EP10: 5 | EQ10: 8 | ER10: 2 | ES10: 1 | ET10: 5 | EU10: 6 | EV10: 4 | EW10: 3 | EX10: 1 | EY10: 4 | EZ10: 8 | FA10: 4 | FB10: 3 | FC10: 3 | FD10: 4 | FE10: 5 | FF10: 6 | FG10: 1 | FH10: 4 | FI10: 0 | FJ10: 4 | FK10: 5 | FL10: 6 | FM10: 2 | FN10: 6 | FO10: 6 | FP10: 7 | FQ10: 3 | FR10: 1 | FS10: 8 | FT10: 8 | FU10: 0 | FV10: 6 | FW10: 4 | FX10: 7 | FY10: 5 | FZ10: 1 | GA10: 2 | GB10: 7 | GC10: 5 | GD10: 5 | GE10: 2 | GF10: 3 | GG10: 1 | GH10: 8 | GI10: 3 | GJ10: 8 | GK10: 5 | GL10: 6 | GM10: 4 | GN10: 8 | GO10: 3 | GP10: 7 | GQ10: 5 | GR10: 5 | GS10: 1 | GT10: 3 | GU10: 3 | GV10: 8 | GW10: 3 | GX10: 4 | GY10: 6 | GZ10: 0 | HA10: 0 | HB10: 7 | HC10: 4 | HD10: 1 | HE10: 7 | HF10: 3 | HG10: 5 | HH10: 4 | HI10: 4 | HJ10: 8 | HK10: 8 | HL10: 8 | HM10: 0 | HN10: 5 | HO10: 2 | HP10: 3 | HQ10: 1 | HR10: 2 | HS10: 7 | HT10: 4 | HU10: 3 | HV10: 5 | HW10: 8 | HX10: 1 | HY10: 2 | HZ10: 7 | IA10: 4 | IB10: 5 | IC10: 1 | ID10: 1 | IE10: 6 | IF10: 7 | IG10: 3 | IH10: 1 | II10: 5 | IJ10: 8 | IK10: 6 | IL10: 7 | IM10: 4 | IN10: 6 | IO10: 1 | IP10: 0 | IQ10: 6 | IR10: 6 | IS10: 6 | IT10: 1 | IU10: 1 | IV10: 6 | IW10: 1 | IX10: 3 | IY10: 4 | IZ10: 0 | JA10: 7 | JB10: 3 | JC10: 6 | JD10: 5 | JE10: 2 | JF10: 6 | JG10: 1 | JH10: 5 | JI10: 6 | JJ10: 4 | JK10: 5 | JL10: 6 | JM10: 3 | JN10: 2 | JO10: 8 | JP10: 1 | JQ10: 1 | JR10: 5 | JS10: 6 | JT10: 7 | JU10: 0 | JV10: 5 | JW10: 5 | JX10: 7 | JY10: 7 | JZ10: 1 | KA10: 6 | KB10: 8 | KC10: 2 | KD10: 0 | KE10: 3 | KF10: 4 | KG10: 4 | KH10: 4 | KI10: 5 | KJ10: 2 | KK10: 1 | KL10: 3 | KM10: 5 | KN10: 7 | KO10: 7 | KP10: 0 | KQ10: 0 | KR10: 4 | KS10: 7 | KT10: 4 | KU10: 6 | KV10: 7 | KW10: 6 | KX10: 5 | KY10: 5 | KZ10: 3 | LA10: 2 | LB10: 3 | LC10: 4 | LD10: 6 | LE10: 5 | LF10: 4 | LG10: 0 | LH10: 1 | LI10: 7 | LJ10: 7 | LK10: 0 | LL10: 3 | LM10: 6 | LN10: 6 | LO10: 1 | LP10: 3 | LQ10: 0 | LR10: 8 | LS10: 1 | LT10: 7 | LU10: 2 | LV10: 5 | LW10: 3 | LX10: 1 | LY10: 1 | LZ10: 0 | MA10: 6 | MB10: 1 | MC10: 8 | MD10: 8 | ME10: 6 | MF10: 0 | MG10: 3 | MH10: 4 | MI10: 8 | MJ10: 5 | MK10: 6 | ML10: 7 | MM10: 6 | MN10: 4 | MO10: 3 | MP10: 6 | MQ10: 7 | MR10: 6 | MS10: 3 | MT10: 1 | MU10: 8 | MV10: 7 | MW10: 4 | MX10: 8 | MY10: 5 | MZ10: 1 | NA10: 3 | NB10: 4 | NE10: =A10 -> G. Michael | NF10: =SUMIF($B$1:$NB$1,NF$1,$B10:$NB10) -> 117 | NG10: =SUMIF($B$1:$NB$1,NG$1,$B10:$NB10) -> 116 | NH10: =SUMIF($B$1:$NB$1,NH$1,$B10:$NB10) -> 115 | NI10: =SUMIF($B$1:$NB$1,NI$1,$B10:$NB10) -> 125 | NJ10: =SUMIF($B$1:$NB$1,NJ$1,$B10:$NB10) -> 139 | NK10: =SUMIF($B$1:$NB$1,NK$1,$B10:$NB10) -> 125 | NL10: =SUMIF($B$1:$NB$1,NL$1,$B10:$NB10) -> 134 | NM10: =SUMIF($B$1:$NB$1,NM$1,$B10:$NB10) -> 131 | ... NQ10: =SUMIF($B$1:$NB$1,NQ$1,$B10:$NB10) -> 140 | NS10: =NE10 -> G. Michael | NT10: 75 | NU10: =$NT10*NF10 -> 8775 | NV10: =$NT10*NG10 -> 8700 | NW10: =$NT10*NH10 -> 8625 | NX10: =$NT10*NI10 -> 9375 | NY10: =$NT10*NJ10 -> 10425 | NZ10: =$NT10*NK10 -> 9375 | OA10: =$NT10*NL10 -> 10050 | OB10: =$NT10*NM10 -> 9825 | ... OF10: =$NT10*NQ10 -> 10500 | OH10: =IF(OF10>12000,"Above","Below") -> Below

Sheet Sales
A1: Order Date | B1: Customer Name | C1: PRODUCT ID | D1: Order Location | E1: Quantity | F1: Book Name | G1: Authors | H1: Book Type | I1: Published Year | J1: Purchase Price | K1: Margin | L1: Selling Price | M1: Month | N1: Sales | O1: Purchase Cost
A2: 41276 | B2: Prabhat Co. | C2: 11 | D2: Store | E2: 13 | F2: =VLOOKUP(C2,Products!$A$2:$H$16,2,FALSE) -> The Discovery of India | G2: =VLOOKUP(C2,Products!$A$2:$H$16,3,FALSE) -> Jawaharlal Nehru | H2: =VLOOKUP(C2,Products!$A$2:$H$16,4,FALSE) -> e-book | I2: =VLOOKUP(C2,Products!$A$2:$H$16,5,FALSE) -> 2004 | J2: =VLOOKUP(C2,Products!$A$2:$H$16,6,FALSE) -> 250 | K2: =VLOOKUP(C2,Products!$A$2:$H$16,7,FALSE) -> 0.3 | L2: =VLOOKUP(C2,Products!$A$2:$H$16,8,FALSE) -> 325 | M2: =MONTH(A2) -> 1 | N2: =L2*E2 -> 4225 | O2: =J2*E2 -> 3250
A3: 41276 | B3: Himtech Corporation | C3: 11 | D3: Store | E3: 5 | F3: =VLOOKUP(C3,Products!$A$2:$H$16,2,FALSE) -> The Discovery of India | G3: =VLOOKUP(C3,Products!$A$2:$H$16,3,FALSE) -> Jawaharlal Nehru | H3: =VLOOKUP(C3,Products!$A$2:$H$16,4,FALSE) -> e-book | I3: =VLOOKUP(C3,Products!$A$2:$H$16,5,FALSE) -> 2004 | J3: =VLOOKUP(C3,Products!$A$2:$H$16,6,FALSE) -> 250 | K3: =VLOOKUP(C3,Products!$A$2:$H$16,7,FALSE) -> 0.3 | L3: =VLOOKUP(C3,Products!$A$2:$H$16,8,FALSE) -> 325 | M3: =MONTH(A3) -> 1 | N3: =L3*E3 -> 1625 | O3: =J3*E3 -> 1250
A4: 41278 | B4: Himtech Corporation | C4: 8 | D4: Store | E4: 10 | F4: =VLOOKUP(C4,Products!$A$2:$H$16,2,FALSE) -> Glimpses of World History | G4: =VLOOKUP(C4,Products!$A$2:$H$16,3,FALSE) -> Jawaharlal Nehru | H4: =VLOOKUP(C4,Products!$A$2:$H$16,4,FALSE) -> Soft Cover | I4: =VLOOKUP(C4,Products!$A$2:$H$16,5,FALSE) -> 1934 | J4: =VLOOKUP(C4,Products!$A$2:$H$16,6,FALSE) -> 650 | K4: =VLOOKUP(C4,Products!$A$2:$H$16,7,FALSE) -> 0.2 | L4: =VLOOKUP(C4,Products!$A$2:$H$16,8,FALSE) -> 780 | M4: =MONTH(A4) -> 1 | N4: =L4*E4 -> 7800 | O4: =J4*E4 -> 6500
A5: 41278 | B5: New Light Co. | C5: 10 | D5: Store | E5: 11 | F5: =VLOOKUP(C5,Products!$A$2:$H$16,2,FALSE) -> Wings of Fire | G5: =VLOOKUP(C5,Products!$A$2:$H$16,3,FALSE) -> APJ Abdul Kalam, Arun Tiwari | H5: =VLOOKUP(C5,Products!$A$2:$H$16,4,FALSE) -> Soft Cover | I5: =VLOOKUP(C5,Products!$A$2:$H$16,5,FALSE) -> 1999 | J5: =VLOOKUP(C5,Products!$A$2:$H$16,6,FALSE) -> 1200 | K5: =VLOOKUP(C5,Products!$A$2:$H$16,7,FALSE) -> 0.1 | L5: =VLOOKUP(C5,Products!$A$2:$H$16,8,FALSE) -> 1320 | M5: =MONTH(A5) -> 1 | N5: =L5*E5 -> 14520 | O5: =J5*E5 -> 13200
A6: 41280 | B6: Anand Co. | C6: 6 | D6: Website | E6: 18 | F6: =VLOOKUP(C6,Products!$A$2:$H$16,2,FALSE) -> The Discovery of India | G6: =VLOOKUP(C6,Products!$A$2:$H$16,3,FALSE) -> Jawaharlal Nehru | H6: =VLOOKUP(C6,Products!$A$2:$H$16,4,FALSE) -> Soft Cover | I6: =VLOOKUP(C6,Products!$A$2:$H$16,5,FALSE) -> 1946 | J6: =VLOOKUP(C6,Products!$A$2:$H$16,6,FALSE) -> 499 | K6: =VLOOKUP(C6,Products!$A$2:$H$16,7,FALSE) -> 0.3 | L6: =VLOOKUP(C6,Products!$A$2:$H$16,8,FALSE) -> 648.7 | M6: =MONTH(A6) -> 1 | N6: =L6*E6 -> 11676.6 | O6: =J6*E6 -> 8982
A7: 41280 | B7: Himtech Corporation | C7: 15 | D7: Store | E7: 12 | F7: =VLOOKUP(C7,Products!$A$2:$H$16,2,FALSE) -> Wings of Fire | G7: =VLOOKUP(C7,Products!$A$2:$H$16,3,FALSE) -> APJ Abdul Kalam, Arun Tiwari | H7: =VLOOKUP(C7,Products!$A$2:$H$16,4,FALSE) -> e-book | I7: =VLOOKUP(C7,Products!$A$2:$H$16,5,FALSE) -> 2005 | J7: =VLOOKUP(C7,Products!$A$2:$H$16,6,FALSE) -> 500 | K7: =VLOOKUP(C7,Products!$A$2:$H$16,7,FALSE) -> 0.1 | L7: =VLOOKUP(C7,Products!$A$2:$H$16,8,FALSE) -> 550 | M7: =MONTH(A7) -> 1 | N7: =L7*E7 -> 6600 | O7: =J7*E7 -> 6000
A8: 41282 | B8: Himtech Corporation | C8: 13 | D8: Website | E8: 6 | F8: =VLOOKUP(C8,Products!$A$2:$H$16,2,FALSE) -> Glimpses of World History | G8: =VLOOKUP(C8,Products!$A$2:$H$16,3,FALSE) -> Jawaharlal Nehru | H8: =VLOOKUP(C8,Products!$A$2:$H$16,4,FALSE) -> e-book | I8: =VLOOKUP(C8,Products!$A$2:$H$16,5,FALSE) -> 2005 | J8: =VLOOKUP(C8,Products!$A$2:$H$16,6,FALSE) -> 300 | K8: =VLOOKUP(C8,Products!$A$2:$H$16,7,FALSE) -> 0.2 | L8: =VLOOKUP(C8,Products!$A$2:$H$16,8,FALSE) -> 360 | M8: =MONTH(A8) -> 1 | N8: =L8*E8 -> 2160 | O8: =J8*E8 -> 1800
A9: 41283 | B9: Bajaj Co. | C9: 4 | D9: Store | E9: 2 | F9: =VLOOKUP(C9,Products!$A$2:$H$16,2,FALSE) -> A Guide to Health | G9: =VLOOKUP(C9,Products!$A$2:$H$16,3,FALSE) -> Mahatma Gandhi | H9: =VLOOKUP(C9,Products!$A$2:$H$16,4,FALSE) -> Hard Cover | I9: =VLOOKUP(C9,Products!$A$2:$H$16,5,FALSE) -> 1921 | J9: =VLOOKUP(C9,Products!$A$2:$H$16,6,FALSE) -> 250 | K9: =VLOOKUP(C9,Products!$A$2:$H$16,7,FALSE) -> 0.15 | L9: =VLOOKUP(C9,Products!$A$2:$H$16,8,FALSE) -> 287.5 | M9: =MONTH(A9) -> 1 | N9: =L9*E9 -> 575 | O9: =J9*E9 -> 500
A10: 41284 | B10: Kalyani Distributors | C10: 4 | D10: Store | E10: 15 | F10: =VLOOKUP(C10,Products!$A$2:$H$16,2,FALSE) -> A Guide to Health | G10: =VLOOKUP(C10,Products!$A$2:$H$16,3,FALSE) -> Mahatma Gandhi | H10: =VLOOKUP(C10,Products!$A$2:$H$16,4,FALSE) -> Hard Cover | I10: =VLOOKUP(C10,Products!$A$2:$H$16,5,FALSE) -> 1921 | J10: =VLOOKUP(C10,Products!$A$2:$H$16,6,FALSE) -> 250 | K10: =VLOOKUP(C10,Products!$A$2:$H$16,7,FALSE) -> 0.15 | L10: =VLOOKUP(C10,Products!$A$2:$H$16,8,FALSE) -> 287.5 | M10: =MONTH(A10) -> 1 | N10: =L10*E10 -> 4312.5 | O10: =J10*E10 -> 3750
A11: 41284 | B11: New Light Co. | C11: 8 | D11: Store | E11: 20 | F11: =VLOOKUP(C11,Products!$A$2:$H$16,2,FALSE) -> Glimpses of World History | G11: =VLOOKUP(C11,Products!$A$2:$H$16,3,FALSE) -> Jawaharlal Nehru | H11: =VLOOKUP(C11,Products!$A$2:$H$16,4,FALSE) -> Soft Cover | I11: =VLOOKUP(C11,Products!$A$2:$H$16,5,FALSE) -> 1934 | J11: =VLOOKUP(C11,Products!$A$2:$H$16,6,FALSE) -> 650 | K11: =VLOOKUP(C11,Products!$A$2:$H$16,7,FALSE) -> 0.2 | L11: =VLOOKUP(C11,Products!$A$2:$H$16,8,FALSE) -> 780 | M11: =MONTH(A11) -> 1 | N11: =L11*E11 -> 15600 | O11: =J11*E11 -> 13000
A12: 41285 | B12: Ajay Co. | C12: 5 | D12: Store | E12: 4 | F12: =VLOOKUP(C12,Products!$A$2:$H$16,2,FALSE) -> Wings of Fire | G12: =VLOOKUP(C12,Products!$A$2:$H$16,3,FALSE) -> APJ Abdul Kalam, Arun Tiwari | H12: =VLOOKUP(C12,Products!$A$2:$H$16,4,FALSE) -> Hard Cover | I12: =VLOOKUP(C12,Products!$A$2:$H$16,5,FALSE) -> 1999 | J12: =VLOOKUP(C12,Products!$A$2:$H$16,6,FALSE) -> 1275.2488 | K12: =VLOOKUP(C12,Products!$A$2:$H$16,7,FALSE) -> 0.1 | L12: =VLOOKUP(C12,Products!$A$2:$H$16,8,FALSE) -> 1402.7737 | M12: =MONTH(A12) -> 1 | N12: =L12*E12 -> 5611.0947 | O12: =J12*E12 -> 5100.9952
A13: 41285 | B13: Bajaj Co. | C13: 1 | D13: Website | E13: 10 | F13: =VLOOKUP(C13,Products!$A$2:$H$16,2,FALSE) -> The Discovery of India | G13: =VLOOKUP(C13,Products!$A$2:$H$16,3,FALSE) -> Jawaharlal Nehru | H13: =VLOOKUP(C13,Products!$A$2:$H$16,4,FALSE) -> Hard Cover | I13: =VLOOKUP(C13,Products!$A$2:$H$16,5,FALSE) -> 1946 | J13: =VLOOKUP(C13,Products!$A$2:$H$16,6,FALSE) -> 599.95 | K13: =VLOOKUP(C13,Products!$A$2:$H$16,7,FALSE) -> 0.3 | L13: =VLOOKUP(C13,Products!$A$2:$H$16,8,FALSE) -> 779.935 | M13: =MONTH(A13) -> 1 | N13: =L13*E13 -> 7799.35 | O13: =J13*E13 -> 5999.5
... A569: 41639 | B569: Ajay Co. | C569: 10 | D569: Store | E569: 7 | F569: =VLOOKUP(C569,Products!$A$2:$H$16,2,FALSE) -> Wings of Fire | G569: =VLOOKUP(C569,Products!$A$2:$H$16,3,FALSE) -> APJ Abdul Kalam, Arun Tiwari | H569: =VLOOKUP(C569,Products!$A$2:$H$16,4,FALSE) -> Soft Cover | I569: =VLOOKUP(C569,Products!$A$2:$H$16,5,FALSE) -> 1999 | J569: =VLOOKUP(C569,Products!$A$2:$H$16,6,FALSE) -> 1200 | K569: =VLOOKUP(C569,Products!$A$2:$H$16,7,FALSE) -> 0.1 | L569: =VLOOKUP(C569,Products!$A$2:$H$16,8,FALSE) -> 1320 | M569: =MONTH(A569) -> 12 | N569: =L569*E569 -> 9240 | O569: =J569*E569 -> 8400

Sheet Report
A5: BOOK TYPE | B5: SALES | D5: MONTH | E5: MONTH NUM | F5: QUANTITY | G5: PURCHASE COST | H5: SALES | I5: PROFIT | K5: BOOK NAME | L5: SALES | M5: QUANTITY
A6: e-book | B6: =SUMIF(Sales!$H$2:$H$569,Report!A6,Sales!$N$2:$N$569) -> 476611 | D6: Jan | E6: 1 | F6: =SUMIF(Sales!$M$2:$M$569,E6,Sales!$E$2:$E$569) -> 506 | G6: =SUMIF(Sales!$M$2:$M$569,E6,Sales!$O$2:$O$569) -> 219868.46 | H6: =SUMIF(Sales!$M$2:$M$569,E6,Sales!$N$2:$N$569) -> 263776.38 | I6: =H6-G6 -> 43907.921 | K6: The Discovery of India | L6: =SUMIF(Sales!$F$2:$F$569,K6,Sales!$N$2:$N$569) -> 691799.16 | M6: =SUMIF(Sales!$F$2:$F$569,K6,Sales!$E$2:$E$569) -> 1230
A7: Hard Cover | B7: =SUMIF(Sales!$H$2:$H$569,Report!A7,Sales!$N$2:$N$569) -> 1391673.8 | D7: Feb | E7: 2 | F7: =SUMIF(Sales!$M$2:$M$569,E7,Sales!$E$2:$E$569) -> 478 | G7: =SUMIF(Sales!$M$2:$M$569,E7,Sales!$O$2:$O$569) -> 234690.81 | H7: =SUMIF(Sales!$M$2:$M$569,E7,Sales!$N$2:$N$569) -> 274770.62 | I7: =H7-G7 -> 40079.808 | K7: The Story of My Experiments with Truth | L7: =SUMIF(Sales!$F$2:$F$569,K7,Sales!$N$2:$N$569) -> 164387.6 | M7: =SUMIF(Sales!$F$2:$F$569,K7,Sales!$E$2:$E$569) -> 1178
A8: Soft Cover | B8: =SUMIF(Sales!$H$2:$H$569,Report!A8,Sales!$N$2:$N$569) -> 1223370.5 | D8: Mar | E8: 3 | F8: =SUMIF(Sales!$M$2:$M$569,E8,Sales!$E$2:$E$569) -> 515 | G8: =SUMIF(Sales!$M$2:$M$569,E8,Sales!$O$2:$O$569) -> 190259.44 | H8: =SUMIF(Sales!$M$2:$M$569,E8,Sales!$N$2:$N$569) -> 227702.49 | I8: =H8-G8 -> 37443.045 | K8: Glimpses of World History | L8: =SUMIF(Sales!$F$2:$F$569,K8,Sales!$N$2:$N$569) -> 853700.53 | M8: =SUMIF(Sales!$F$2:$F$569,K8,Sales!$E$2:$E$569) -> 1212
D9: Apr | E9: 4 | F9: =SUMIF(Sales!$M$2:$M$569,E9,Sales!$E$2:$E$569) -> 464 | G9: =SUMIF(Sales!$M$2:$M$569,E9,Sales!$O$2:$O$569) -> 221708.32 | H9: =SUMIF(Sales!$M$2:$M$569,E9,Sales!$N$2:$N$569) -> 261835.06 | I9: =H9-G9 -> 40126.733 | K9: A Guide to Health | L9: =SUMIF(Sales!$F$2:$F$569,K9,Sales!$N$2:$N$569) -> 265029 | M9: =SUMIF(Sales!$F$2:$F$569,K9,Sales!$E$2:$E$569) -> 1185
D10: May | E10: 5 | F10: =SUMIF(Sales!$M$2:$M$569,E10,Sales!$E$2:$E$569) -> 420 | G10: =SUMIF(Sales!$M$2:$M$569,E10,Sales!$O$2:$O$569) -> 193509.75 | H10: =SUMIF(Sales!$M$2:$M$569,E10,Sales!$N$2:$N$569) -> 225204.88 | I10: =H10-G10 -> 31695.131 | K10: Wings of Fire | L10: =SUMIF(Sales!$F$2:$F$569,K10,Sales!$N$2:$N$569) -> 1116739 | M10: =SUMIF(Sales!$F$2:$F$569,K10,Sales!$E$2:$E$569) -> 961
A11: ORDER LOCATION | B11: SALES | D11: Jun | E11: 6 | F11: =SUMIF(Sales!$M$2:$M$569,E11,Sales!$E$2:$E$569) -> 605 | G11: =SUMIF(Sales!$M$2:$M$569,E11,Sales!$O$2:$O$569) -> 291749.85 | H11: =SUMIF(Sales!$M$2:$M$569,E11,Sales!$N$2:$N$569) -> 341768.92 | I11: =H11-G11 -> 50019.068
A12: Store | B12: =SUMIF(Sales!$D$2:$D$569,A12,Sales!$N$2:$N$569) -> 1588744.3 | D12: Jul | E12: 7 | F12: =SUMIF(Sales!$M$2:$M$569,E12,Sales!$E$2:$E$569) -> 526 | G12: =SUMIF(Sales!$M$2:$M$569,E12,Sales!$O$2:$O$569) -> 253365.46 | H12: =SUMIF(Sales!$M$2:$M$569,E12,Sales!$N$2:$N$569) -> 293877.33 | I12: =H12-G12 -> 40511.867 | K12: CUSTOMER | L12: SALES
A13: Website | B13: =SUMIF(Sales!$D$2:$D$569,A13,Sales!$N$2:$N$569) -> 1502911 | D13: Aug | E13: 8 | F13: =SUMIF(Sales!$M$2:$M$569,E13,Sales!$E$2:$E$569) -> 510 | G13: =SUMIF(Sales!$M$2:$M$569,E13,Sales!$O$2:$O$569) -> 260050.4 | H13: =SUMIF(Sales!$M$2:$M$569,E13,Sales!$N$2:$N$569) -> 308298.39 | I13: =H13-G13 -> 48247.986 | K13: Prabhat Co. | L13: =SUMIF(Sales!$B$2:$B$569,K13,Sales!$N$2:$N$569) -> 310438.25
D14: Sep | E14: 9 | F14: =SUMIF(Sales!$M$2:$M$569,E14,Sales!$E$2:$E$569) -> 362 | G14: =SUMIF(Sales!$M$2:$M$569,E14,Sales!$O$2:$O$569) -> 126667.67 | H14: =SUMIF(Sales!$M$2:$M$569,E14,Sales!$N$2:$N$569) -> 154370.96 | I14: =H14-G14 -> 27703.29 | K14: Himtech Corporation | L14: =SUMIF(Sales!$B$2:$B$569,K14,Sales!$N$2:$N$569) -> 377859.16
D15: Oct | E15: 10 | F15: =SUMIF(Sales!$M$2:$M$569,E15,Sales!$E$2:$E$569) -> 352 | G15: =SUMIF(Sales!$M$2:$M$569,E15,Sales!$O$2:$O$569) -> 170990.28 | H15: =SUMIF(Sales!$M$2:$M$569,E15,Sales!$N$2:$N$569) -> 203968.87 | I15: =H15-G15 -> 32978.589 | K15: New Light Co. | L15: =SUMIF(Sales!$B$2:$B$569,K15,Sales!$N$2:$N$569) -> 446595.03
D16: Nov | E16: 11 | F16: =SUMIF(Sales!$M$2:$M$569,E16,Sales!$E$2:$E$569) -> 563 | G16: =SUMIF(Sales!$M$2:$M$569,E16,Sales!$O$2:$O$569) -> 275347.33 | H16: =SUMIF(Sales!$M$2:$M$569,E16,Sales!$N$2:$N$569) -> 324133.52 | I16: =H16-G16 -> 48786.193 | K16: Anand Co. | L16: =SUMIF(Sales!$B$2:$B$569,K16,Sales!$N$2:$N$569) -> 360315.96
D17: Dec | E17: 12 | F17: =SUMIF(Sales!$M$2:$M$569,E17,Sales!$E$2:$E$569) -> 465 | G17: =SUMIF(Sales!$M$2:$M$569,E17,Sales!$O$2:$O$569) -> 177491.84 | H17: =SUMIF(Sales!$M$2:$M$569,E17,Sales!$N$2:$N$569) -> 211947.92 | I17: =H17-G17 -> 34456.08 | K17: Bajaj Co. | L17: =SUMIF(Sales!$B$2:$B$569,K17,Sales!$N$2:$N$569) -> 413380.56
K18: Kalyani Distributors | L18: =SUMIF(Sales!$B$2:$B$569,K18,Sales!$N$2:$N$569) -> 420092.46
K19: Ajay Co. | L19: =SUMIF(Sales!$B$2:$B$569,K19,Sales!$N$2:$N$569) -> 301205.22
K20: Sohan's Co. | L20: =SUMIF(Sales!$B$2:$B$569,K20,Sales!$N$2:$N$569) -> 461768.67
